{
  "schemaVersion": 3,
  "updatedAt": "2026-05-30T11:15:03.321Z",
  "source": {
    "primaryAttempt": "Pump.fun frontend API",
    "active": "DexScreener public API fallback",
    "endpoint": "https://api.dexscreener.com/token-boosts/top/v1",
    "blocker": "Pump.fun frontend API returned 403 and redirected/blocked non-browser fetches.",
    "providers": [
      "DexScreener public API fallback",
      "GeckoTerminal Solana trending pools",
      "CoinGecko solana-meme-coins",
      "Raydium top-liquidity pools (70)",
      "Jupiter /swap/v1/quote (tradability)"
    ],
    "poolSize": 101,
    "schema": "dailyRadar/trending/highCap/lowCap + per-row sources[]+confidence"
  },
  "dailyRadar": [
    {
      "rank": 1,
      "name": "cummunity",
      "symbol": "CUM",
      "mint": "oqU4DdYCbdSf9j74vnEgvCn1YzNfYQEPWaC6pu6pump",
      "imageUrl": "https://coin-images.coingecko.com/coins/images/102173546/large/8odvi9zrd881gni8bnltztl83e23.?1780127112",
      "pumpFunUrl": "https://pump.fun/coin/oqU4DdYCbdSf9j74vnEgvCn1YzNfYQEPWaC6pu6pump",
      "fallbackUrl": "https://www.geckoterminal.com/solana/pools/GKDdjR8Nm4Y1m4KTWb9LYLMpvTH48W1tEdx85oqD1Wcu",
      "label": "Daily Radar pick",
      "sourceName": "GeckoTerminal",
      "priceUsd": 0.0014032744965153032,
      "priceChange24h": 4527.365,
      "marketCapUsd": 1403228.25885801,
      "volume24hUsd": 8395209.50260893,
      "liquidityUsd": 113727.1346,
      "coingeckoId": "cummunity",
      "lastUpdated": "2026-05-30T11:15:02.631Z",
      "sources": [
        "gecko-terminal"
      ],
      "confidence": 1,
      "momentumScore": 2266.748,
      "tradable": false
    },
    {
      "rank": 2,
      "name": "ももちゃん",
      "symbol": "MOMO",
      "mint": "Gsks4bWgKUCaBA6yzQSrBCAmbLbEtLEHXMMaUshxpump",
      "imageUrl": "https://assets.geckoterminal.com/qd8g62g4u3jx7dhcrf0kb0uweyse",
      "pumpFunUrl": "https://pump.fun/coin/Gsks4bWgKUCaBA6yzQSrBCAmbLbEtLEHXMMaUshxpump",
      "fallbackUrl": "https://www.geckoterminal.com/solana/pools/D6QWD4ybnMByDweu1px76UDGoxUkc9KuZbcuFqbQk83F",
      "label": "Daily Radar pick",
      "sourceName": "GeckoTerminal",
      "priceUsd": 0.0006461122756938475,
      "priceChange24h": 1859.553,
      "marketCapUsd": 648695.2722,
      "volume24hUsd": 1756954.99372924,
      "liquidityUsd": 69464.5397,
      "lastUpdated": "2026-05-30T11:15:02.631Z",
      "sources": [
        "gecko-terminal"
      ],
      "confidence": 1,
      "momentumScore": 932.624,
      "tradable": false
    },
    {
      "rank": 3,
      "name": "Killer Bill",
      "symbol": "KB",
      "mint": "kSrKKcfp9dJHWsxdYZuWtpXqXANmptdkTakB4YEpump",
      "imageUrl": "https://cdn.dexscreener.com/cms/images/skfRoPrZGZg_WiH8?width=800&height=800&quality=95&format=auto",
      "pumpFunUrl": "https://pump.fun/coin/kSrKKcfp9dJHWsxdYZuWtpXqXANmptdkTakB4YEpump",
      "fallbackUrl": "https://dexscreener.com/solana/ksrkkcfp9djhwsxdyzuwtpxqxanmptdktakb4yepump",
      "label": "Daily Radar pick",
      "sourceName": "Public meme radar",
      "priceUsd": 0.0006481,
      "priceChange24h": 950,
      "marketCapUsd": 648147,
      "volume24hUsd": 1151621.93,
      "lastUpdated": "2026-05-30T11:15:02.073Z",
      "sources": [
        "dexscreener"
      ],
      "confidence": 1,
      "momentumScore": 477.084,
      "tradable": false
    }
  ],
  "trending": [
    {
      "rank": 1,
      "name": "genny.tech",
      "symbol": "GENNY",
      "mint": "BkCVgVcKS1u5j18w9Gt2P4vA2ws5DLRGmJkzfkUJpump",
      "imageUrl": "https://cdn.dexscreener.com/cms/images/gY-Q8wtBVkD9JJh8?width=800&height=800&quality=95&format=auto",
      "pumpFunUrl": "https://pump.fun/coin/BkCVgVcKS1u5j18w9Gt2P4vA2ws5DLRGmJkzfkUJpump",
      "fallbackUrl": "https://dexscreener.com/solana/bkcvgvcks1u5j18w9gt2p4va2ws5dlrgmjkzfkujpump",
      "label": "High-cap Pump.fun coin",
      "sourceName": "Public meme radar",
      "priceUsd": 0.0000231,
      "priceChange24h": 889,
      "marketCapUsd": 23101.08,
      "volume24hUsd": 29226.11,
      "lastUpdated": "2026-05-30T11:15:02.073Z",
      "sources": [
        "dexscreener"
      ],
      "confidence": 1
    },
    {
      "rank": 2,
      "name": "ballish",
      "symbol": "BALLISH",
      "mint": "CmGsBfi3Zbsygpt1FcvFcQa3mD2drYGX6w5WdsWZpump",
      "imageUrl": "https://assets.geckoterminal.com/brdgbppqqthn3ynq6z3nf74wlx29",
      "pumpFunUrl": "https://pump.fun/coin/CmGsBfi3Zbsygpt1FcvFcQa3mD2drYGX6w5WdsWZpump",
      "fallbackUrl": "https://www.geckoterminal.com/solana/pools/6ZfY55nrvu2bpcHEX1ZfpcUkPyvqGWWiy5iL3YQz7Qr7",
      "label": "GeckoTerminal trending pool",
      "sourceName": "GeckoTerminal",
      "priceUsd": 0.00029925662488725904,
      "priceChange24h": 766.72,
      "marketCapUsd": 303189.1685,
      "volume24hUsd": 1299858.689175,
      "liquidityUsd": 46254.9093,
      "lastUpdated": "2026-05-30T11:15:02.631Z",
      "sources": [
        "gecko-terminal"
      ],
      "confidence": 1
    },
    {
      "rank": 3,
      "name": "The Last X Community",
      "symbol": "Community",
      "mint": "8dqQtM7eDQeamYMRnQw5dSV73byyKkogLuMKz3ykpump",
      "imageUrl": "https://cdn.dexscreener.com/cms/images/H56z0zy4JB6lhJ1K?width=800&height=800&quality=95&format=auto",
      "pumpFunUrl": "https://pump.fun/coin/8dqQtM7eDQeamYMRnQw5dSV73byyKkogLuMKz3ykpump",
      "fallbackUrl": "https://dexscreener.com/solana/8dqqtm7edqeamymrnqw5dsv73byykkoglumkz3ykpump",
      "label": "High-cap Pump.fun coin",
      "sourceName": "Public meme radar",
      "priceUsd": 0.00001511,
      "priceChange24h": 496,
      "marketCapUsd": 15117.87,
      "volume24hUsd": 52374.26,
      "lastUpdated": "2026-05-30T11:15:02.073Z",
      "sources": [
        "dexscreener"
      ],
      "confidence": 1
    },
    {
      "rank": 4,
      "name": "Oklahoma City Thunder",
      "symbol": "OKC",
      "mint": "GQASup5cYyHupWSvGMhQy4Gm79wFPWPg9D3oUmppump",
      "imageUrl": "https://cdn.dexscreener.com/cms/images/rqxazkmygFI3NcaF?width=800&height=800&quality=95&format=auto",
      "pumpFunUrl": "https://pump.fun/coin/GQASup5cYyHupWSvGMhQy4Gm79wFPWPg9D3oUmppump",
      "fallbackUrl": "https://dexscreener.com/solana/gqasup5cyyhupwsvgmhqy4gm79wfpwpg9d3oumppump",
      "label": "Boosted Pump.fun coin",
      "sourceName": "Public meme radar",
      "priceUsd": 0.00001437,
      "priceChange24h": 360,
      "marketCapUsd": 14373.15,
      "volume24hUsd": 82746.15,
      "lastUpdated": "2026-05-30T11:15:02.073Z",
      "sources": [
        "dexscreener"
      ],
      "confidence": 1
    },
    {
      "rank": 5,
      "name": "Kätalyst",
      "symbol": "Kätalyst",
      "mint": "7XujDi97puebmckBPsrSAYg44epkuwm2qT5TND1Xpump",
      "imageUrl": "https://cdn.dexscreener.com/cms/images/AdRckHmK-0pAbRp5?width=800&height=800&quality=95&format=auto",
      "pumpFunUrl": "https://pump.fun/coin/7XujDi97puebmckBPsrSAYg44epkuwm2qT5TND1Xpump",
      "fallbackUrl": "https://dexscreener.com/solana/7xujdi97puebmckbpsrsayg44epkuwm2qt5tnd1xpump",
      "label": "High-cap Pump.fun coin",
      "sourceName": "Public meme radar",
      "priceUsd": 0.00001272,
      "priceChange24h": 356,
      "marketCapUsd": 12721.41,
      "volume24hUsd": 141794.78,
      "lastUpdated": "2026-05-30T11:15:02.073Z",
      "sources": [
        "dexscreener"
      ],
      "confidence": 1
    },
    {
      "rank": 6,
      "name": "The Company",
      "symbol": "COMPANY",
      "mint": "8fuoMSAMxPXCYGq3h7GTfGYxsaULghVuz5jPHXoTpump",
      "imageUrl": "https://cdn.dexscreener.com/cms/images/VFg-mbOZU57aPwVm?width=800&height=800&quality=95&format=auto",
      "pumpFunUrl": "https://pump.fun/coin/8fuoMSAMxPXCYGq3h7GTfGYxsaULghVuz5jPHXoTpump",
      "fallbackUrl": "https://dexscreener.com/solana/8fuomsamxpxcygq3h7gtfgyxsaulghvuz5jphxotpump",
      "label": "High-cap Pump.fun coin",
      "sourceName": "Public meme radar",
      "priceUsd": 0.000009437,
      "priceChange24h": 272,
      "marketCapUsd": 9437.02,
      "volume24hUsd": 13271.87,
      "lastUpdated": "2026-05-30T11:15:02.073Z",
      "sources": [
        "dexscreener"
      ],
      "confidence": 1
    },
    {
      "rank": 7,
      "name": "The Rally Rabbit",
      "symbol": "Rally",
      "mint": "5UErAnwSnGBPRkhxSjKiswMemr1uipvMPHLFfZrDpump",
      "imageUrl": "https://cdn.dexscreener.com/cms/images/1bFV3QCdHTS2_13R?width=800&height=800&quality=95&format=auto",
      "pumpFunUrl": "https://pump.fun/coin/5UErAnwSnGBPRkhxSjKiswMemr1uipvMPHLFfZrDpump",
      "fallbackUrl": "https://dexscreener.com/solana/5ueranwsngbprkhxsjkiswmemr1uipvmphlffzrdpump",
      "label": "High-cap Pump.fun coin",
      "sourceName": "Public meme radar",
      "priceUsd": 0.00001222,
      "priceChange24h": 250,
      "marketCapUsd": 12220.67,
      "volume24hUsd": 87516.88,
      "lastUpdated": "2026-05-30T11:15:02.073Z",
      "sources": [
        "dexscreener"
      ],
      "confidence": 1
    },
    {
      "rank": 8,
      "name": "The Mouse As Big As The Elephant",
      "symbol": "🐁 🐘",
      "mint": "4pXLCBkbq98KmdSxQhG3UHPDvhRPx76XbSD7zAQSpump",
      "imageUrl": "https://cdn.dexscreener.com/cms/images/SnBOq6wcuwJ3rtUf?width=800&height=800&quality=95&format=auto",
      "pumpFunUrl": "https://pump.fun/coin/4pXLCBkbq98KmdSxQhG3UHPDvhRPx76XbSD7zAQSpump",
      "fallbackUrl": "https://dexscreener.com/solana/4pxlcbkbq98kmdsxqhg3uhpdvhrpx76xbsd7zaqspump",
      "label": "High-cap Pump.fun coin",
      "sourceName": "Public meme radar",
      "priceUsd": 0.000009264,
      "priceChange24h": 233,
      "marketCapUsd": 9264.11,
      "volume24hUsd": 106551.68,
      "lastUpdated": "2026-05-30T11:15:02.073Z",
      "sources": [
        "dexscreener"
      ],
      "confidence": 1
    },
    {
      "rank": 9,
      "name": "The Eternal Dog",
      "symbol": "Hachiko",
      "mint": "CJuAc61eawmEmfJ4XjgKUTPQ2uNZXxLnMmMXqxQUpump",
      "imageUrl": "https://cdn.dexscreener.com/cms/images/L3rXmA3VDFpZ_Q_3?width=800&height=800&quality=95&format=auto",
      "pumpFunUrl": "https://pump.fun/coin/CJuAc61eawmEmfJ4XjgKUTPQ2uNZXxLnMmMXqxQUpump",
      "fallbackUrl": "https://dexscreener.com/solana/cjuac61eawmemfj4xjgkutpq2unzxxlnmmmxqxqupump",
      "label": "High-cap Pump.fun coin",
      "sourceName": "Public meme radar",
      "priceUsd": 0.000008448,
      "priceChange24h": 224,
      "marketCapUsd": 8448.46,
      "volume24hUsd": 34531.64,
      "lastUpdated": "2026-05-30T11:15:02.073Z",
      "sources": [
        "dexscreener"
      ],
      "confidence": 1
    },
    {
      "rank": 10,
      "name": "PRIDE TROLL",
      "symbol": "PRIDETROLL",
      "mint": "APDCqK5jpSR2YjNxTH6dKJzFwvGcjdQx5kPevU2gpump",
      "imageUrl": "https://cdn.dexscreener.com/cms/images/M_kIBg8LDYeAIzi2?width=800&height=800&quality=95&format=auto",
      "pumpFunUrl": "https://pump.fun/coin/APDCqK5jpSR2YjNxTH6dKJzFwvGcjdQx5kPevU2gpump",
      "fallbackUrl": "https://dexscreener.com/solana/apdcqk5jpsr2yjnxth6dkjzfwvgcjdqx5kpevu2gpump",
      "label": "High-cap Pump.fun coin",
      "sourceName": "Public meme radar",
      "priceUsd": 0.000008763,
      "priceChange24h": 209,
      "marketCapUsd": 8763.31,
      "volume24hUsd": 10710.13,
      "lastUpdated": "2026-05-30T11:15:02.073Z",
      "sources": [
        "dexscreener"
      ],
      "confidence": 1
    },
    {
      "rank": 11,
      "name": "Bubo",
      "symbol": "BUBO",
      "mint": "DZBff9C2LXgTSyy5WpG2UDzKSKVVYmi4vPjzdV9Spump",
      "imageUrl": "https://cdn.dexscreener.com/cms/images/zhgrtjQZYA9Z1EWo?width=800&height=800&quality=95&format=auto",
      "pumpFunUrl": "https://pump.fun/coin/DZBff9C2LXgTSyy5WpG2UDzKSKVVYmi4vPjzdV9Spump",
      "fallbackUrl": "https://dexscreener.com/solana/dzbff9c2lxgtsyy5wpg2udzkskvvymi4vpjzdv9spump",
      "label": "Boosted Pump.fun coin",
      "sourceName": "Public meme radar",
      "priceUsd": 0.00008511,
      "priceChange24h": 149,
      "marketCapUsd": 85113,
      "volume24hUsd": 461445.45,
      "lastUpdated": "2026-05-30T11:15:02.073Z",
      "sources": [
        "dexscreener",
        "gecko-terminal"
      ],
      "liquidityUsd": 22364.6288,
      "confidence": 2
    },
    {
      "rank": 12,
      "name": "Dogeus Maximus",
      "symbol": "DOGEUS",
      "mint": "FeMrhDeddUvuzo25RZriZD6Te8xy3tdyKLLXBhEEpump",
      "imageUrl": "https://cdn.dexscreener.com/cms/images/B5SWnMr_53RU5XsC?width=800&height=800&quality=95&format=auto",
      "pumpFunUrl": "https://pump.fun/coin/FeMrhDeddUvuzo25RZriZD6Te8xy3tdyKLLXBhEEpump",
      "fallbackUrl": "https://dexscreener.com/solana/femrhdedduvuzo25rzrizd6te8xy3tdykllxbheepump",
      "label": "Boosted Pump.fun coin",
      "sourceName": "Public meme radar",
      "priceUsd": 0.0001937,
      "priceChange24h": 130,
      "marketCapUsd": 193746,
      "volume24hUsd": 755932.9,
      "lastUpdated": "2026-05-30T11:15:02.073Z",
      "sources": [
        "dexscreener",
        "gecko-terminal"
      ],
      "liquidityUsd": 35936.1431,
      "coingeckoId": "dogeus-maximus",
      "confidence": 2
    },
    {
      "rank": 13,
      "name": "Baby Troll",
      "symbol": "BABYTROLL",
      "mint": "baby-troll-4",
      "imageUrl": "https://coin-images.coingecko.com/coins/images/102173234/large/mgkdrr7d0y3059w4nw2xx36ggxz0.?1778494269",
      "pumpFunUrl": "",
      "fallbackUrl": "https://www.coingecko.com/en/coins/baby-troll-4",
      "label": "CoinGecko Solana meme",
      "sourceName": "CoinGecko",
      "priceUsd": 0.00073014,
      "priceChange24h": 125.72895,
      "marketCapUsd": 700501,
      "volume24hUsd": 1033695,
      "lastUpdated": "2026-05-30T11:15:02.487Z",
      "sources": [
        "coingecko"
      ],
      "confidence": 1
    },
    {
      "rank": 14,
      "name": "Baby Troll",
      "symbol": "BABYTROLL",
      "mint": "6qdzMx4c9rL2X3Ns3SwZ8uEo4zReDPjdXpAEmpo7pump",
      "imageUrl": "https://coin-images.coingecko.com/coins/images/102173234/large/mgkdrr7d0y3059w4nw2xx36ggxz0.?1778494269",
      "pumpFunUrl": "https://pump.fun/coin/6qdzMx4c9rL2X3Ns3SwZ8uEo4zReDPjdXpAEmpo7pump",
      "fallbackUrl": "https://www.geckoterminal.com/solana/pools/34UtPx3zyYfC5GVqDXWJqLf77BU5Ebb6o3C2XynpKtzL",
      "label": "GeckoTerminal trending pool",
      "sourceName": "GeckoTerminal",
      "priceUsd": 0.0007259254030216305,
      "priceChange24h": 116.615,
      "marketCapUsd": 710887.627455141,
      "volume24hUsd": 903579.145846172,
      "liquidityUsd": 98382.1928,
      "coingeckoId": "baby-troll-4",
      "lastUpdated": "2026-05-30T11:15:02.631Z",
      "sources": [
        "gecko-terminal"
      ],
      "confidence": 1
    },
    {
      "rank": 15,
      "name": "SpaceX",
      "symbol": "SPCX",
      "mint": "E6ifp2mJy8cYQehUGUtFvrXriRKxRuonLmrvTFypump",
      "imageUrl": "https://cdn.dexscreener.com/cms/images/6ai5LnHxCQmAz07b?width=800&height=800&quality=95&format=auto",
      "pumpFunUrl": "https://pump.fun/coin/E6ifp2mJy8cYQehUGUtFvrXriRKxRuonLmrvTFypump",
      "fallbackUrl": "https://dexscreener.com/solana/e6ifp2mjy8cyqehugutfvrxrirkxruonlmrvtfypump",
      "label": "Boosted Pump.fun coin",
      "sourceName": "Public meme radar",
      "priceUsd": 0.004251,
      "priceChange24h": 102,
      "marketCapUsd": 4250047,
      "volume24hUsd": 1236029.22,
      "lastUpdated": "2026-05-30T11:15:02.073Z",
      "sources": [
        "dexscreener",
        "gecko-terminal"
      ],
      "liquidityUsd": 237424.8928,
      "confidence": 2
    },
    {
      "rank": 16,
      "name": "New Elon Dog",
      "symbol": "CALI",
      "mint": "7BGXDFP9FLdK8bLmGyV7BdvvkdN1QTdDPsap4pztpump",
      "imageUrl": "https://cdn.dexscreener.com/cms/images/CAzAhB8a85fU19E-?width=800&height=800&quality=95&format=auto",
      "pumpFunUrl": "https://pump.fun/coin/7BGXDFP9FLdK8bLmGyV7BdvvkdN1QTdDPsap4pztpump",
      "fallbackUrl": "https://dexscreener.com/solana/7bgxdfp9fldk8blmgyv7bdvvkdn1qtddpsap4pztpump",
      "label": "Boosted Pump.fun coin",
      "sourceName": "Public meme radar",
      "priceUsd": 0.000004582,
      "priceChange24h": 100,
      "marketCapUsd": 4582.36,
      "volume24hUsd": 67803.21,
      "lastUpdated": "2026-05-30T11:15:02.073Z",
      "sources": [
        "dexscreener"
      ],
      "confidence": 1
    },
    {
      "rank": 17,
      "name": "Law Of Attraction",
      "symbol": "LOA",
      "mint": "EhHyfjRwj2jhmSE7GW5uJfizaLcNDa5C4HWPiSqjpump",
      "imageUrl": "https://cdn.dexscreener.com/cms/images/5GlcoW3WmVegL7e3?width=800&height=800&quality=95&format=auto",
      "pumpFunUrl": "https://pump.fun/coin/EhHyfjRwj2jhmSE7GW5uJfizaLcNDa5C4HWPiSqjpump",
      "fallbackUrl": "https://dexscreener.com/solana/ehhyfjrwj2jhmse7gw5ujfizalcnda5c4hwpisqjpump",
      "label": "Boosted Pump.fun coin",
      "sourceName": "Public meme radar",
      "priceUsd": 0.0007671,
      "priceChange24h": 62.91,
      "marketCapUsd": 767128,
      "volume24hUsd": 303818.34,
      "lastUpdated": "2026-05-30T11:15:02.073Z",
      "sources": [
        "dexscreener",
        "gecko-terminal"
      ],
      "liquidityUsd": 68330.824,
      "coingeckoId": "law-of-attraction-3",
      "confidence": 2
    },
    {
      "rank": 18,
      "name": "Just Hold $8 Worth",
      "symbol": "8",
      "mint": "vhBZqcbfJvtqp3Bu48xB9JQQ6z66vBLwTGW7dK5pump",
      "imageUrl": "https://coin-images.coingecko.com/coins/images/102173548/large/gwjoa7xsqsdois8u5m5zvc2asrsf.?1780128211",
      "pumpFunUrl": "https://pump.fun/coin/vhBZqcbfJvtqp3Bu48xB9JQQ6z66vBLwTGW7dK5pump",
      "fallbackUrl": "https://www.geckoterminal.com/solana/pools/3zjE3G8ZtCLDkENDwSYYmbjmaaZTobHG4DWrQ1TK6ADx",
      "label": "GeckoTerminal trending pool",
      "sourceName": "GeckoTerminal",
      "priceUsd": 0.00004693710507174027,
      "priceChange24h": 53.637,
      "marketCapUsd": 46932.047724933,
      "volume24hUsd": 1785377.2332328,
      "liquidityUsd": 19020.5521,
      "coingeckoId": "just-hold-8-worth",
      "lastUpdated": "2026-05-30T11:15:02.631Z",
      "sources": [
        "gecko-terminal"
      ],
      "confidence": 1
    },
    {
      "rank": 19,
      "name": "TOESCOIN",
      "symbol": "TOES",
      "mint": "toescoin",
      "imageUrl": "https://coin-images.coingecko.com/coins/images/102173370/large/111111.png?1779223810",
      "pumpFunUrl": "",
      "fallbackUrl": "https://www.coingecko.com/en/coins/toescoin",
      "label": "CoinGecko Solana meme",
      "sourceName": "CoinGecko",
      "priceUsd": 0.01129732,
      "priceChange24h": 49.72765,
      "marketCapUsd": 11345818,
      "volume24hUsd": 2321084,
      "lastUpdated": "2026-05-30T11:15:02.487Z",
      "sources": [
        "coingecko"
      ],
      "confidence": 1
    },
    {
      "rank": 20,
      "name": "TOES",
      "symbol": "TOESCOIN",
      "mint": "6ehEcTMCc85aNF4x9CWx8HuvWGhxQtvKdhKVf2HDpump",
      "imageUrl": "https://cdn.dexscreener.com/cms/images/eEd07gpIegaJRCp3?width=800&height=800&quality=95&format=auto",
      "pumpFunUrl": "https://pump.fun/coin/6ehEcTMCc85aNF4x9CWx8HuvWGhxQtvKdhKVf2HDpump",
      "fallbackUrl": "https://dexscreener.com/solana/6ehectmcc85anf4x9cwx8huvwghxqtvkdhkvf2hdpump",
      "label": "Boosted Pump.fun coin",
      "sourceName": "Public meme radar",
      "priceUsd": 0.01131,
      "priceChange24h": 47.65,
      "marketCapUsd": 11316196,
      "volume24hUsd": 2379734.71,
      "lastUpdated": "2026-05-30T11:15:02.073Z",
      "sources": [
        "dexscreener",
        "gecko-terminal"
      ],
      "liquidityUsd": 293008.1751,
      "coingeckoId": "toescoin",
      "confidence": 2
    },
    {
      "rank": 21,
      "name": "Mikawa Inu",
      "symbol": "SHIKOKU",
      "mint": "5Jng6jkLKU1o8BNrCzTEMXMFvPjNJZTpdWR3Hq4RHJb6",
      "imageUrl": "https://coin-images.coingecko.com/coins/images/51034/large/photo_2024-10-27_22.09.24.png?1730081890",
      "pumpFunUrl": "",
      "fallbackUrl": "https://www.geckoterminal.com/solana/pools/FyQuZLz6LLJxKhSwXkMpZ5Po6G8bcRv8Ub2s3paU74pC",
      "label": "GeckoTerminal trending pool",
      "sourceName": "GeckoTerminal",
      "priceUsd": 1.4904988020054649e-9,
      "priceChange24h": 36.594,
      "marketCapUsd": 1492047.98055096,
      "volume24hUsd": 754355.916438529,
      "liquidityUsd": 128173.2734,
      "coingeckoId": "mikawa-inu-2",
      "lastUpdated": "2026-05-30T11:15:02.631Z",
      "sources": [
        "gecko-terminal"
      ],
      "confidence": 1
    },
    {
      "rank": 22,
      "name": "Spettro - AI Agent CLI",
      "symbol": "SPETTRO",
      "mint": "C3fawupKrXdn3X7KPTmmnkwzJQ9qycMNag55ZzQ8pump",
      "imageUrl": "https://coin-images.coingecko.com/coins/images/102173540/large/bksnpf29g30q4qwvo0y9be2zdil8.?1780066736",
      "pumpFunUrl": "https://pump.fun/coin/C3fawupKrXdn3X7KPTmmnkwzJQ9qycMNag55ZzQ8pump",
      "fallbackUrl": "https://www.geckoterminal.com/solana/pools/CDQAkPCbP6TykEz1UwwEpQtBcEXo6mZZH652JRiPwW6r",
      "label": "GeckoTerminal trending pool",
      "sourceName": "GeckoTerminal",
      "priceUsd": 0.0004378072831250588,
      "priceChange24h": 34.587,
      "marketCapUsd": 437949.120873246,
      "volume24hUsd": 718528.30314928,
      "liquidityUsd": 55822.0245,
      "coingeckoId": "spettro-ai-agent-cli",
      "lastUpdated": "2026-05-30T11:15:02.631Z",
      "sources": [
        "gecko-terminal"
      ],
      "confidence": 1
    },
    {
      "rank": 23,
      "name": "Chill House",
      "symbol": "CHILLHOUSE",
      "mint": "chill-house",
      "imageUrl": "https://coin-images.coingecko.com/coins/images/55535/large/1irHeiVg_400x400.jpg?1746563474",
      "pumpFunUrl": "",
      "fallbackUrl": "https://www.coingecko.com/en/coins/chill-house",
      "label": "CoinGecko Solana meme",
      "sourceName": "CoinGecko",
      "priceUsd": 0.00275698,
      "priceChange24h": 23.46913,
      "marketCapUsd": 2753702,
      "volume24hUsd": 1310792,
      "lastUpdated": "2026-05-30T11:15:02.487Z",
      "sources": [
        "coingecko"
      ],
      "confidence": 1
    },
    {
      "rank": 24,
      "name": "Toylor Swift",
      "symbol": "Toylor",
      "mint": "D5erbncxYamGZmy5DzsVjQ1ybJbvGLsUJGFWrtzUpump",
      "imageUrl": "https://cdn.dexscreener.com/cms/images/Ei4UiWeZ2Qw0eqim?width=800&height=800&quality=95&format=auto",
      "pumpFunUrl": "https://pump.fun/coin/D5erbncxYamGZmy5DzsVjQ1ybJbvGLsUJGFWrtzUpump",
      "fallbackUrl": "https://dexscreener.com/solana/d5erbncxyamgzmy5dzsvjq1ybjbvglsujgfwrtzupump",
      "label": "High-cap Pump.fun coin",
      "sourceName": "Public meme radar",
      "priceUsd": 0.00004167,
      "priceChange24h": 21.97,
      "marketCapUsd": 41676,
      "volume24hUsd": 356238.84,
      "lastUpdated": "2026-05-30T11:15:02.073Z",
      "sources": [
        "dexscreener"
      ],
      "confidence": 1
    },
    {
      "rank": 25,
      "name": "aura",
      "symbol": "AURA",
      "mint": "aura-on-sol",
      "imageUrl": "https://coin-images.coingecko.com/coins/images/38376/large/aura_logo_200x200-01-01.png?1751114135",
      "pumpFunUrl": "",
      "fallbackUrl": "https://www.coingecko.com/en/coins/aura-on-sol",
      "label": "CoinGecko Solana meme",
      "sourceName": "CoinGecko",
      "priceUsd": 0.0180285,
      "priceChange24h": 21.73739,
      "marketCapUsd": 17441648,
      "volume24hUsd": 1807952,
      "lastUpdated": "2026-05-30T11:15:02.487Z",
      "sources": [
        "coingecko"
      ],
      "confidence": 1
    },
    {
      "rank": 26,
      "name": "TROLL",
      "symbol": "TROLL",
      "mint": "troll-2",
      "imageUrl": "https://coin-images.coingecko.com/coins/images/55282/large/Untitled_design.png?1777015928",
      "pumpFunUrl": "",
      "fallbackUrl": "https://www.coingecko.com/en/coins/troll-2",
      "label": "CoinGecko Solana meme",
      "sourceName": "CoinGecko",
      "priceUsd": 0.08867,
      "priceChange24h": 20.92576,
      "marketCapUsd": 88331338,
      "volume24hUsd": 10092421,
      "lastUpdated": "2026-05-30T11:15:02.487Z",
      "sources": [
        "coingecko"
      ],
      "confidence": 1
    },
    {
      "rank": 27,
      "name": "TROLL",
      "symbol": "TROLL",
      "mint": "5UUH9RTDiSpq6HKS6bp4NdU9PNJpXRXuiw6ShBTBhgH2",
      "imageUrl": "https://coin-images.coingecko.com/coins/images/55282/large/Untitled_design.png?1777015928",
      "pumpFunUrl": "",
      "fallbackUrl": "https://www.geckoterminal.com/solana/pools/4w2cysotX6czaUGmmWg13hDpY4QEMG2CzeKYEQyK9Ama",
      "label": "GeckoTerminal trending pool",
      "sourceName": "GeckoTerminal",
      "priceUsd": 0.08854360678572146,
      "priceChange24h": 20.607,
      "marketCapUsd": 88434911.1449577,
      "volume24hUsd": 3603656.86638297,
      "liquidityUsd": 3552082.1677,
      "coingeckoId": "troll-2",
      "lastUpdated": "2026-05-30T11:15:02.631Z",
      "sources": [
        "gecko-terminal"
      ],
      "confidence": 1
    },
    {
      "rank": 28,
      "name": "SpaceExplorationTechnologiesCorp",
      "symbol": "SPCX",
      "mint": "26YRpwvWhTSBSAkQbhNP6AXBNrJe8uRxibAn7ZXXpump",
      "imageUrl": "https://cdn.dexscreener.com/cms/images/etlEYrLXlwugk3S0?width=800&height=800&quality=95&format=auto",
      "pumpFunUrl": "https://pump.fun/coin/26YRpwvWhTSBSAkQbhNP6AXBNrJe8uRxibAn7ZXXpump",
      "fallbackUrl": "https://dexscreener.com/solana/26yrpwvwhtsbsakqbhnp6axbnrje8urxiban7zxxpump",
      "label": "Boosted Pump.fun coin",
      "sourceName": "Public meme radar",
      "priceUsd": 0.0003847,
      "priceChange24h": 19.87,
      "marketCapUsd": 382504,
      "volume24hUsd": 84268.99,
      "lastUpdated": "2026-05-30T11:15:02.073Z",
      "sources": [
        "dexscreener"
      ],
      "confidence": 1
    },
    {
      "rank": 29,
      "name": "Manifesting",
      "symbol": "MANIFEST",
      "mint": "BCdwQBAn8dYB5YjTsoB6TdHAWokxv28k2oZUodERpump",
      "imageUrl": "https://cdn.dexscreener.com/cms/images/r9S-l7wVI3T4YrGJ?width=800&height=800&quality=95&format=auto",
      "pumpFunUrl": "https://pump.fun/coin/BCdwQBAn8dYB5YjTsoB6TdHAWokxv28k2oZUodERpump",
      "fallbackUrl": "https://dexscreener.com/solana/bcdwqban8dyb5yjtsob6tdhawokxv28k2ozuoderpump",
      "label": "Boosted Pump.fun coin",
      "sourceName": "Public meme radar",
      "priceUsd": 0.02835,
      "priceChange24h": 19.56,
      "marketCapUsd": 25520214,
      "volume24hUsd": 1172244.44,
      "lastUpdated": "2026-05-30T11:15:02.073Z",
      "sources": [
        "dexscreener",
        "gecko-terminal"
      ],
      "liquidityUsd": 660422.7628,
      "coingeckoId": "manifesting",
      "confidence": 2
    },
    {
      "rank": 30,
      "name": "Manifesting",
      "symbol": "MANIFEST",
      "mint": "manifesting",
      "imageUrl": "https://coin-images.coingecko.com/coins/images/102173340/large/manifesting.jpg?1779374701",
      "pumpFunUrl": "",
      "fallbackUrl": "https://www.coingecko.com/en/coins/manifesting",
      "label": "CoinGecko Solana meme",
      "sourceName": "CoinGecko",
      "priceUsd": 0.02827008,
      "priceChange24h": 18.95063,
      "marketCapUsd": 25292668,
      "volume24hUsd": 1166793,
      "lastUpdated": "2026-05-30T11:15:02.487Z",
      "sources": [
        "coingecko"
      ],
      "confidence": 1
    }
  ],
  "highCap": [
    {
      "rank": 1,
      "name": "Pudgy Penguins",
      "symbol": "PENGU",
      "mint": "pudgy-penguins",
      "imageUrl": "https://coin-images.coingecko.com/coins/images/52622/large/PUDGY_PENGUINS_PENGU_PFP.png?1733809110",
      "pumpFunUrl": "",
      "fallbackUrl": "https://www.coingecko.com/en/coins/pudgy-penguins",
      "label": "High-cap",
      "sourceName": "CoinGecko",
      "priceUsd": 0.00800676,
      "priceChange24h": 3.75017,
      "marketCapUsd": 502921524,
      "volume24hUsd": 115085109,
      "lastUpdated": "2026-05-30T11:15:02.487Z",
      "sources": [
        "coingecko"
      ],
      "confidence": 1
    },
    {
      "rank": 2,
      "name": "Bonk",
      "symbol": "BONK",
      "mint": "bonk",
      "imageUrl": "https://coin-images.coingecko.com/coins/images/28600/large/bonk.jpg?1696527587",
      "pumpFunUrl": "",
      "fallbackUrl": "https://www.coingecko.com/en/coins/bonk",
      "label": "High-cap",
      "sourceName": "CoinGecko",
      "priceUsd": 0.00000547,
      "priceChange24h": -0.03043,
      "marketCapUsd": 481905612,
      "volume24hUsd": 31083479,
      "lastUpdated": "2026-05-30T11:15:02.487Z",
      "sources": [
        "coingecko"
      ],
      "confidence": 1
    },
    {
      "rank": 3,
      "name": "Official Trump",
      "symbol": "TRUMP",
      "mint": "official-trump",
      "imageUrl": "https://coin-images.coingecko.com/coins/images/53746/large/trump.png?1737171561",
      "pumpFunUrl": "",
      "fallbackUrl": "https://www.coingecko.com/en/coins/official-trump",
      "label": "High-cap",
      "sourceName": "CoinGecko",
      "priceUsd": 2,
      "priceChange24h": 4.73056,
      "marketCapUsd": 475875073,
      "volume24hUsd": 99840757,
      "lastUpdated": "2026-05-30T11:15:02.487Z",
      "sources": [
        "coingecko"
      ],
      "confidence": 1
    },
    {
      "rank": 4,
      "name": "dogwifhat",
      "symbol": "WIF",
      "mint": "dogwifcoin",
      "imageUrl": "https://coin-images.coingecko.com/coins/images/33566/large/dogwifhat.jpg?1702499428",
      "pumpFunUrl": "",
      "fallbackUrl": "https://www.coingecko.com/en/coins/dogwifcoin",
      "label": "High-cap",
      "sourceName": "CoinGecko",
      "priceUsd": 0.1911,
      "priceChange24h": 2.14662,
      "marketCapUsd": 191156467,
      "volume24hUsd": 36457315,
      "lastUpdated": "2026-05-30T11:15:02.487Z",
      "sources": [
        "coingecko"
      ],
      "confidence": 1
    },
    {
      "rank": 5,
      "name": "Fartcoin",
      "symbol": "FARTCOIN",
      "mint": "fartcoin",
      "imageUrl": "https://coin-images.coingecko.com/coins/images/50891/large/fart.jpg?1729503972",
      "pumpFunUrl": "",
      "fallbackUrl": "https://www.coingecko.com/en/coins/fartcoin",
      "label": "High-cap",
      "sourceName": "CoinGecko",
      "priceUsd": 0.160102,
      "priceChange24h": -1.66733,
      "marketCapUsd": 160100366,
      "volume24hUsd": 28172037,
      "lastUpdated": "2026-05-30T11:15:02.487Z",
      "sources": [
        "coingecko"
      ],
      "confidence": 1
    },
    {
      "rank": 6,
      "name": "Melania Meme",
      "symbol": "MELANIA",
      "mint": "melania-meme",
      "imageUrl": "https://coin-images.coingecko.com/coins/images/53775/large/melania-meme.png?1737329885",
      "pumpFunUrl": "",
      "fallbackUrl": "https://www.coingecko.com/en/coins/melania-meme",
      "label": "High-cap",
      "sourceName": "CoinGecko",
      "priceUsd": 0.092868,
      "priceChange24h": 2.40708,
      "marketCapUsd": 88584860,
      "volume24hUsd": 7199330,
      "lastUpdated": "2026-05-30T11:15:02.487Z",
      "sources": [
        "coingecko"
      ],
      "confidence": 1
    },
    {
      "rank": 7,
      "name": "TROLL",
      "symbol": "TROLL",
      "mint": "5UUH9RTDiSpq6HKS6bp4NdU9PNJpXRXuiw6ShBTBhgH2",
      "imageUrl": "https://coin-images.coingecko.com/coins/images/55282/large/Untitled_design.png?1777015928",
      "pumpFunUrl": "",
      "fallbackUrl": "https://www.geckoterminal.com/solana/pools/4w2cysotX6czaUGmmWg13hDpY4QEMG2CzeKYEQyK9Ama",
      "label": "High-cap",
      "sourceName": "GeckoTerminal",
      "priceUsd": 0.08854360678572146,
      "priceChange24h": 20.607,
      "marketCapUsd": 88434911.1449577,
      "volume24hUsd": 3603656.86638297,
      "liquidityUsd": 3552082.1677,
      "coingeckoId": "troll-2",
      "lastUpdated": "2026-05-30T11:15:02.631Z",
      "sources": [
        "gecko-terminal"
      ],
      "confidence": 1
    },
    {
      "rank": 8,
      "name": "TROLL",
      "symbol": "TROLL",
      "mint": "troll-2",
      "imageUrl": "https://coin-images.coingecko.com/coins/images/55282/large/Untitled_design.png?1777015928",
      "pumpFunUrl": "",
      "fallbackUrl": "https://www.coingecko.com/en/coins/troll-2",
      "label": "High-cap",
      "sourceName": "CoinGecko",
      "priceUsd": 0.08867,
      "priceChange24h": 20.92576,
      "marketCapUsd": 88331338,
      "volume24hUsd": 10092421,
      "lastUpdated": "2026-05-30T11:15:02.487Z",
      "sources": [
        "coingecko"
      ],
      "confidence": 1
    },
    {
      "rank": 9,
      "name": "Useless Coin",
      "symbol": "USELESS",
      "mint": "useless-3",
      "imageUrl": "https://coin-images.coingecko.com/coins/images/55684/large/coingeckoupdate.png?1755203747",
      "pumpFunUrl": "",
      "fallbackUrl": "https://www.coingecko.com/en/coins/useless-3",
      "label": "High-cap",
      "sourceName": "CoinGecko",
      "priceUsd": 0.072469,
      "priceChange24h": 5.90662,
      "marketCapUsd": 72742650,
      "volume24hUsd": 9081572,
      "lastUpdated": "2026-05-30T11:15:02.487Z",
      "sources": [
        "coingecko"
      ],
      "confidence": 1
    },
    {
      "rank": 10,
      "name": "Baby Doge Coin",
      "symbol": "BABYDOGE",
      "mint": "baby-doge-coin",
      "imageUrl": "https://coin-images.coingecko.com/coins/images/16125/large/babydoge.jpg?1696515731",
      "pumpFunUrl": "",
      "fallbackUrl": "https://www.coingecko.com/en/coins/baby-doge-coin",
      "label": "High-cap",
      "sourceName": "CoinGecko",
      "priceUsd": 3.95287e-10,
      "priceChange24h": 3.79333,
      "marketCapUsd": 72525749,
      "volume24hUsd": 3370296,
      "lastUpdated": "2026-05-30T11:15:02.487Z",
      "sources": [
        "coingecko"
      ],
      "confidence": 1
    },
    {
      "rank": 11,
      "name": "Comedian",
      "symbol": "BAN",
      "mint": "comedian",
      "imageUrl": "https://coin-images.coingecko.com/coins/images/51100/large/ban.jpg?1730085215",
      "pumpFunUrl": "",
      "fallbackUrl": "https://www.coingecko.com/en/coins/comedian",
      "label": "High-cap",
      "sourceName": "CoinGecko",
      "priceUsd": 0.067177,
      "priceChange24h": -4.10506,
      "marketCapUsd": 67272578,
      "volume24hUsd": 7317710,
      "lastUpdated": "2026-05-30T11:15:02.487Z",
      "sources": [
        "coingecko"
      ],
      "confidence": 1
    },
    {
      "rank": 12,
      "name": "Dog (Bitcoin)",
      "symbol": "DOG",
      "mint": "dog-go-to-the-moon-rune",
      "imageUrl": "https://coin-images.coingecko.com/coins/images/37352/large/DOGGOTOTHEMOON.png?1714096969",
      "pumpFunUrl": "",
      "fallbackUrl": "https://www.coingecko.com/en/coins/dog-go-to-the-moon-rune",
      "label": "High-cap",
      "sourceName": "CoinGecko",
      "priceUsd": 0.00063494,
      "priceChange24h": 1.00439,
      "marketCapUsd": 63491800,
      "volume24hUsd": 1662089,
      "lastUpdated": "2026-05-30T11:15:02.487Z",
      "sources": [
        "coingecko"
      ],
      "confidence": 1
    },
    {
      "rank": 13,
      "name": "Peanut the Squirrel",
      "symbol": "PNUT",
      "mint": "peanut-the-squirrel",
      "imageUrl": "https://coin-images.coingecko.com/coins/images/51301/large/Peanut_the_Squirrel.png?1734941241",
      "pumpFunUrl": "",
      "fallbackUrl": "https://www.coingecko.com/en/coins/peanut-the-squirrel",
      "label": "High-cap",
      "sourceName": "CoinGecko",
      "priceUsd": 0.052151,
      "priceChange24h": -1.19101,
      "marketCapUsd": 52296239,
      "volume24hUsd": 9445012,
      "lastUpdated": "2026-05-30T11:15:02.487Z",
      "sources": [
        "coingecko"
      ],
      "confidence": 1
    },
    {
      "rank": 14,
      "name": "Popcat",
      "symbol": "POPCAT",
      "mint": "popcat",
      "imageUrl": "https://coin-images.coingecko.com/coins/images/33760/large/image.jpg?1702964227",
      "pumpFunUrl": "",
      "fallbackUrl": "https://www.coingecko.com/en/coins/popcat",
      "label": "High-cap",
      "sourceName": "CoinGecko",
      "priceUsd": 0.052443,
      "priceChange24h": 2.19532,
      "marketCapUsd": 51407040,
      "volume24hUsd": 11468359,
      "lastUpdated": "2026-05-30T11:15:02.487Z",
      "sources": [
        "coingecko"
      ],
      "confidence": 1
    },
    {
      "rank": 15,
      "name": "Moo Deng",
      "symbol": "MOODENG",
      "mint": "moo-deng",
      "imageUrl": "https://coin-images.coingecko.com/coins/images/50264/large/MOODENG.jpg?1726726975",
      "pumpFunUrl": "",
      "fallbackUrl": "https://www.coingecko.com/en/coins/moo-deng",
      "label": "High-cap",
      "sourceName": "CoinGecko",
      "priceUsd": 0.050287,
      "priceChange24h": 1.41346,
      "marketCapUsd": 49870973,
      "volume24hUsd": 9702314,
      "lastUpdated": "2026-05-30T11:15:02.487Z",
      "sources": [
        "coingecko"
      ],
      "confidence": 1
    },
    {
      "rank": 16,
      "name": "cat in a dogs world",
      "symbol": "MEW",
      "mint": "cat-in-a-dogs-world",
      "imageUrl": "https://coin-images.coingecko.com/coins/images/36440/large/MEW.png?1711442286",
      "pumpFunUrl": "",
      "fallbackUrl": "https://www.coingecko.com/en/coins/cat-in-a-dogs-world",
      "label": "High-cap",
      "sourceName": "CoinGecko",
      "priceUsd": 0.00050495,
      "priceChange24h": 2.72968,
      "marketCapUsd": 44927189,
      "volume24hUsd": 4805610,
      "lastUpdated": "2026-05-30T11:15:02.487Z",
      "sources": [
        "coingecko"
      ],
      "confidence": 1
    },
    {
      "rank": 17,
      "name": "Not in Employment, Education, or Training",
      "symbol": "NEET",
      "mint": "neet",
      "imageUrl": "https://coin-images.coingecko.com/coins/images/55411/large/neet.jpg?1745850587",
      "pumpFunUrl": "",
      "fallbackUrl": "https://www.coingecko.com/en/coins/neet",
      "label": "High-cap",
      "sourceName": "CoinGecko",
      "priceUsd": 0.03901378,
      "priceChange24h": 10.3879,
      "marketCapUsd": 39078986,
      "volume24hUsd": 1916698,
      "lastUpdated": "2026-05-30T11:15:02.487Z",
      "sources": [
        "coingecko"
      ],
      "confidence": 1
    },
    {
      "rank": 18,
      "name": "BOOK OF MEME",
      "symbol": "BOME",
      "mint": "book-of-meme",
      "imageUrl": "https://coin-images.coingecko.com/coins/images/36071/large/bome.png?1710407255",
      "pumpFunUrl": "",
      "fallbackUrl": "https://www.coingecko.com/en/coins/book-of-meme",
      "label": "High-cap",
      "sourceName": "CoinGecko",
      "priceUsd": 0.00049592,
      "priceChange24h": -0.08493,
      "marketCapUsd": 34241247,
      "volume24hUsd": 9339169,
      "lastUpdated": "2026-05-30T11:15:02.487Z",
      "sources": [
        "coingecko"
      ],
      "confidence": 1
    },
    {
      "rank": 19,
      "name": "Gigachad",
      "symbol": "GIGA",
      "mint": "gigachad-2",
      "imageUrl": "https://coin-images.coingecko.com/coins/images/34755/large/IMG_0015.png?1705957165",
      "pumpFunUrl": "",
      "fallbackUrl": "https://www.coingecko.com/en/coins/gigachad-2",
      "label": "High-cap",
      "sourceName": "CoinGecko",
      "priceUsd": 0.00333572,
      "priceChange24h": 1.24543,
      "marketCapUsd": 32054551,
      "volume24hUsd": 1593914,
      "lastUpdated": "2026-05-30T11:15:02.487Z",
      "sources": [
        "coingecko"
      ],
      "confidence": 1
    },
    {
      "rank": 20,
      "name": "Moonbirds",
      "symbol": "BIRB",
      "mint": "moonbirds",
      "imageUrl": "https://coin-images.coingecko.com/coins/images/69732/large/birb-logo.jpg?1759413928",
      "pumpFunUrl": "",
      "fallbackUrl": "https://www.coingecko.com/en/coins/moonbirds",
      "label": "High-cap",
      "sourceName": "CoinGecko",
      "priceUsd": 0.100642,
      "priceChange24h": -0.80086,
      "marketCapUsd": 28670371,
      "volume24hUsd": 3578336,
      "lastUpdated": "2026-05-30T11:15:02.487Z",
      "sources": [
        "coingecko"
      ],
      "confidence": 1
    },
    {
      "rank": 21,
      "name": "Manifesting",
      "symbol": "MANIFEST",
      "mint": "BCdwQBAn8dYB5YjTsoB6TdHAWokxv28k2oZUodERpump",
      "imageUrl": "https://cdn.dexscreener.com/cms/images/r9S-l7wVI3T4YrGJ?width=800&height=800&quality=95&format=auto",
      "pumpFunUrl": "https://pump.fun/coin/BCdwQBAn8dYB5YjTsoB6TdHAWokxv28k2oZUodERpump",
      "fallbackUrl": "https://dexscreener.com/solana/bcdwqban8dyb5yjtsob6tdhawokxv28k2ozuoderpump",
      "label": "High-cap",
      "sourceName": "Public meme radar",
      "priceUsd": 0.02835,
      "priceChange24h": 19.56,
      "marketCapUsd": 25520214,
      "volume24hUsd": 1172244.44,
      "lastUpdated": "2026-05-30T11:15:02.073Z",
      "sources": [
        "dexscreener",
        "gecko-terminal"
      ],
      "liquidityUsd": 660422.7628,
      "coingeckoId": "manifesting",
      "confidence": 2
    },
    {
      "rank": 22,
      "name": "Manifesting",
      "symbol": "MANIFEST",
      "mint": "manifesting",
      "imageUrl": "https://coin-images.coingecko.com/coins/images/102173340/large/manifesting.jpg?1779374701",
      "pumpFunUrl": "",
      "fallbackUrl": "https://www.coingecko.com/en/coins/manifesting",
      "label": "High-cap",
      "sourceName": "CoinGecko",
      "priceUsd": 0.02827008,
      "priceChange24h": 18.95063,
      "marketCapUsd": 25292668,
      "volume24hUsd": 1166793,
      "lastUpdated": "2026-05-30T11:15:02.487Z",
      "sources": [
        "coingecko"
      ],
      "confidence": 1
    },
    {
      "rank": 23,
      "name": "Zerebro",
      "symbol": "ZEREBRO",
      "mint": "zerebro",
      "imageUrl": "https://coin-images.coingecko.com/coins/images/51289/large/zerebro_2.png?1730588883",
      "pumpFunUrl": "",
      "fallbackUrl": "https://www.coingecko.com/en/coins/zerebro",
      "label": "High-cap",
      "sourceName": "CoinGecko",
      "priceUsd": 0.02197528,
      "priceChange24h": -13.10922,
      "marketCapUsd": 22080836,
      "volume24hUsd": 4497602,
      "lastUpdated": "2026-05-30T11:15:02.487Z",
      "sources": [
        "coingecko"
      ],
      "confidence": 1
    },
    {
      "rank": 24,
      "name": "pippin",
      "symbol": "PIPPIN",
      "mint": "pippin",
      "imageUrl": "https://coin-images.coingecko.com/coins/images/51589/large/pippin_logo.png?1731570163",
      "pumpFunUrl": "",
      "fallbackUrl": "https://www.coingecko.com/en/coins/pippin",
      "label": "High-cap",
      "sourceName": "CoinGecko",
      "priceUsd": 0.01909816,
      "priceChange24h": 0.97611,
      "marketCapUsd": 19107745,
      "volume24hUsd": 3720009,
      "lastUpdated": "2026-05-30T11:15:02.487Z",
      "sources": [
        "coingecko"
      ],
      "confidence": 1
    },
    {
      "rank": 25,
      "name": "PONKE",
      "symbol": "PONKE",
      "mint": "ponke",
      "imageUrl": "https://coin-images.coingecko.com/coins/images/33929/large/ponke-logo.png?1747200908",
      "pumpFunUrl": "",
      "fallbackUrl": "https://www.coingecko.com/en/coins/ponke",
      "label": "High-cap",
      "sourceName": "CoinGecko",
      "priceUsd": 0.03293403,
      "priceChange24h": -1.51696,
      "marketCapUsd": 18283886,
      "volume24hUsd": 1715792,
      "lastUpdated": "2026-05-30T11:15:02.487Z",
      "sources": [
        "coingecko"
      ],
      "confidence": 1
    },
    {
      "rank": 26,
      "name": "aura",
      "symbol": "AURA",
      "mint": "aura-on-sol",
      "imageUrl": "https://coin-images.coingecko.com/coins/images/38376/large/aura_logo_200x200-01-01.png?1751114135",
      "pumpFunUrl": "",
      "fallbackUrl": "https://www.coingecko.com/en/coins/aura-on-sol",
      "label": "High-cap",
      "sourceName": "CoinGecko",
      "priceUsd": 0.0180285,
      "priceChange24h": 21.73739,
      "marketCapUsd": 17441648,
      "volume24hUsd": 1807952,
      "lastUpdated": "2026-05-30T11:15:02.487Z",
      "sources": [
        "coingecko"
      ],
      "confidence": 1
    },
    {
      "rank": 27,
      "name": "Goatseus Maximus",
      "symbol": "GOAT",
      "mint": "goatseus-maximus",
      "imageUrl": "https://coin-images.coingecko.com/coins/images/50717/large/GOAT_LOGO_NEW.jpg?1731292759",
      "pumpFunUrl": "",
      "fallbackUrl": "https://www.coingecko.com/en/coins/goatseus-maximus",
      "label": "High-cap",
      "sourceName": "CoinGecko",
      "priceUsd": 0.01607697,
      "priceChange24h": 0.30198,
      "marketCapUsd": 16234300,
      "volume24hUsd": 5890874,
      "lastUpdated": "2026-05-30T11:15:02.487Z",
      "sources": [
        "coingecko"
      ],
      "confidence": 1
    },
    {
      "rank": 28,
      "name": "Vine",
      "symbol": "VINE",
      "mint": "vine",
      "imageUrl": "https://coin-images.coingecko.com/coins/images/53859/large/vine.jpg?1737613523",
      "pumpFunUrl": "",
      "fallbackUrl": "https://www.coingecko.com/en/coins/vine",
      "label": "High-cap",
      "sourceName": "CoinGecko",
      "priceUsd": 0.01605827,
      "priceChange24h": 1.04611,
      "marketCapUsd": 16059739,
      "volume24hUsd": 4156222,
      "lastUpdated": "2026-05-30T11:15:02.487Z",
      "sources": [
        "coingecko"
      ],
      "confidence": 1
    },
    {
      "rank": 29,
      "name": "Bertram The Pomeranian",
      "symbol": "BERT",
      "mint": "bertram-the-pomeranian",
      "imageUrl": "https://coin-images.coingecko.com/coins/images/51480/large/photo_2025-04-22_23.04.39.png?1745405423",
      "pumpFunUrl": "",
      "fallbackUrl": "https://www.coingecko.com/en/coins/bertram-the-pomeranian",
      "label": "High-cap",
      "sourceName": "CoinGecko",
      "priceUsd": 0.01326179,
      "priceChange24h": -3.47163,
      "marketCapUsd": 12984273,
      "volume24hUsd": 998776,
      "lastUpdated": "2026-05-30T11:15:02.487Z",
      "sources": [
        "coingecko"
      ],
      "confidence": 1
    },
    {
      "rank": 30,
      "name": "Buttcoin",
      "symbol": "BUTTCOIN",
      "mint": "buttcoin-7",
      "imageUrl": "https://coin-images.coingecko.com/coins/images/71595/large/IMG_3410.PNG?1768472819",
      "pumpFunUrl": "",
      "fallbackUrl": "https://www.coingecko.com/en/coins/buttcoin-7",
      "label": "High-cap",
      "sourceName": "CoinGecko",
      "priceUsd": 0.01185808,
      "priceChange24h": 0.78356,
      "marketCapUsd": 11956861,
      "volume24hUsd": 1128638,
      "lastUpdated": "2026-05-30T11:15:02.487Z",
      "sources": [
        "coingecko"
      ],
      "confidence": 1
    }
  ],
  "lowCap": [
    {
      "rank": 1,
      "name": "Tofu the Golden Retriever",
      "symbol": "TOFULING",
      "mint": "3BmfmP7UY6LxoW7ibkDCXhzkzkARpCgr3Sk6KHc9pump",
      "imageUrl": "https://cdn.dexscreener.com/cms/images/hfosq7vAQmG46xVa?width=800&height=800&quality=95&format=auto",
      "pumpFunUrl": "https://pump.fun/coin/3BmfmP7UY6LxoW7ibkDCXhzkzkARpCgr3Sk6KHc9pump",
      "fallbackUrl": "https://dexscreener.com/solana/3bmfmp7uy6lxow7ibkdcxhzkzkarpcgr3sk6khc9pump",
      "label": "Low-cap discovery",
      "sourceName": "Public meme radar",
      "priceUsd": 0.000004533,
      "priceChange24h": -86.14,
      "marketCapUsd": 4532,
      "volume24hUsd": 4600479.49,
      "lastUpdated": "2026-05-30T11:15:02.072Z",
      "sources": [
        "dexscreener"
      ],
      "confidence": 1
    },
    {
      "rank": 2,
      "name": "Just Hold $8 Worth",
      "symbol": "8",
      "mint": "vhBZqcbfJvtqp3Bu48xB9JQQ6z66vBLwTGW7dK5pump",
      "imageUrl": "https://coin-images.coingecko.com/coins/images/102173548/large/gwjoa7xsqsdois8u5m5zvc2asrsf.?1780128211",
      "pumpFunUrl": "https://pump.fun/coin/vhBZqcbfJvtqp3Bu48xB9JQQ6z66vBLwTGW7dK5pump",
      "fallbackUrl": "https://www.geckoterminal.com/solana/pools/3zjE3G8ZtCLDkENDwSYYmbjmaaZTobHG4DWrQ1TK6ADx",
      "label": "Low-cap discovery",
      "sourceName": "GeckoTerminal",
      "priceUsd": 0.00004693710507174027,
      "priceChange24h": 53.637,
      "marketCapUsd": 46932.047724933,
      "volume24hUsd": 1785377.2332328,
      "liquidityUsd": 19020.5521,
      "coingeckoId": "just-hold-8-worth",
      "lastUpdated": "2026-05-30T11:15:02.631Z",
      "sources": [
        "gecko-terminal"
      ],
      "confidence": 1
    },
    {
      "rank": 3,
      "name": "ballish",
      "symbol": "BALLISH",
      "mint": "CmGsBfi3Zbsygpt1FcvFcQa3mD2drYGX6w5WdsWZpump",
      "imageUrl": "https://assets.geckoterminal.com/brdgbppqqthn3ynq6z3nf74wlx29",
      "pumpFunUrl": "https://pump.fun/coin/CmGsBfi3Zbsygpt1FcvFcQa3mD2drYGX6w5WdsWZpump",
      "fallbackUrl": "https://www.geckoterminal.com/solana/pools/6ZfY55nrvu2bpcHEX1ZfpcUkPyvqGWWiy5iL3YQz7Qr7",
      "label": "Low-cap discovery",
      "sourceName": "GeckoTerminal",
      "priceUsd": 0.00029925662488725904,
      "priceChange24h": 766.72,
      "marketCapUsd": 303189.1685,
      "volume24hUsd": 1299858.689175,
      "liquidityUsd": 46254.9093,
      "lastUpdated": "2026-05-30T11:15:02.631Z",
      "sources": [
        "gecko-terminal"
      ],
      "confidence": 1
    },
    {
      "rank": 4,
      "name": "Just Buy $250 Worth",
      "symbol": "250",
      "mint": "BUG9jJ6MZcxbXaDVqq199HvWafMSP4pYHVFrZfLmpump",
      "imageUrl": "https://assets.geckoterminal.com/blprxs1slstol3v3gy35vttplgzu",
      "pumpFunUrl": "https://pump.fun/coin/BUG9jJ6MZcxbXaDVqq199HvWafMSP4pYHVFrZfLmpump",
      "fallbackUrl": "https://www.geckoterminal.com/solana/pools/C3W4oqFjiFEKLdqUpa23htx1HZ7byK4HsCgnetP2gwmU",
      "label": "Low-cap discovery",
      "sourceName": "GeckoTerminal",
      "priceUsd": 0.00016477114384150064,
      "priceChange24h": -79.352,
      "marketCapUsd": 162404.2606,
      "volume24hUsd": 819238.804112469,
      "liquidityUsd": 47627.2548,
      "lastUpdated": "2026-05-30T11:15:02.631Z",
      "sources": [
        "gecko-terminal"
      ],
      "confidence": 1
    },
    {
      "rank": 5,
      "name": "aliens.gov",
      "symbol": "ALIENS",
      "mint": "C9UM3Bf43GDHMi4wM3BkqpqQ3DovYn8hqTfx21zipump",
      "imageUrl": "https://coin-images.coingecko.com/coins/images/102173536/large/3ejthhlv1337pmb3jykmrorklwga.?1780064767",
      "pumpFunUrl": "https://pump.fun/coin/C9UM3Bf43GDHMi4wM3BkqpqQ3DovYn8hqTfx21zipump",
      "fallbackUrl": "https://www.geckoterminal.com/solana/pools/5xa29ffmANcT7J7LX47pqDEK51DhukALcP8H9Dz8R6dP",
      "label": "Low-cap discovery",
      "sourceName": "GeckoTerminal",
      "priceUsd": 0.00006370823195249494,
      "priceChange24h": -69.346,
      "marketCapUsd": 63947.419921153,
      "volume24hUsd": 765561.75559042,
      "liquidityUsd": 22825.4425,
      "coingeckoId": "aliens-gov-2",
      "lastUpdated": "2026-05-30T11:15:02.631Z",
      "sources": [
        "gecko-terminal"
      ],
      "confidence": 1
    },
    {
      "rank": 6,
      "name": "Dogeus Maximus",
      "symbol": "DOGEUS",
      "mint": "FeMrhDeddUvuzo25RZriZD6Te8xy3tdyKLLXBhEEpump",
      "imageUrl": "https://cdn.dexscreener.com/cms/images/B5SWnMr_53RU5XsC?width=800&height=800&quality=95&format=auto",
      "pumpFunUrl": "https://pump.fun/coin/FeMrhDeddUvuzo25RZriZD6Te8xy3tdyKLLXBhEEpump",
      "fallbackUrl": "https://dexscreener.com/solana/femrhdedduvuzo25rzrizd6te8xy3tdykllxbheepump",
      "label": "Low-cap discovery",
      "sourceName": "Public meme radar",
      "priceUsd": 0.0001937,
      "priceChange24h": 130,
      "marketCapUsd": 193746,
      "volume24hUsd": 755932.9,
      "lastUpdated": "2026-05-30T11:15:02.073Z",
      "sources": [
        "dexscreener",
        "gecko-terminal"
      ],
      "liquidityUsd": 35936.1431,
      "coingeckoId": "dogeus-maximus",
      "confidence": 2
    },
    {
      "rank": 7,
      "name": "Spettro - AI Agent CLI",
      "symbol": "SPETTRO",
      "mint": "C3fawupKrXdn3X7KPTmmnkwzJQ9qycMNag55ZzQ8pump",
      "imageUrl": "https://coin-images.coingecko.com/coins/images/102173540/large/bksnpf29g30q4qwvo0y9be2zdil8.?1780066736",
      "pumpFunUrl": "https://pump.fun/coin/C3fawupKrXdn3X7KPTmmnkwzJQ9qycMNag55ZzQ8pump",
      "fallbackUrl": "https://www.geckoterminal.com/solana/pools/CDQAkPCbP6TykEz1UwwEpQtBcEXo6mZZH652JRiPwW6r",
      "label": "Low-cap discovery",
      "sourceName": "GeckoTerminal",
      "priceUsd": 0.0004378072831250588,
      "priceChange24h": 34.587,
      "marketCapUsd": 437949.120873246,
      "volume24hUsd": 718528.30314928,
      "liquidityUsd": 55822.0245,
      "coingeckoId": "spettro-ai-agent-cli",
      "lastUpdated": "2026-05-30T11:15:02.631Z",
      "sources": [
        "gecko-terminal"
      ],
      "confidence": 1
    },
    {
      "rank": 8,
      "name": "Memecoin Packs",
      "symbol": "PACKS",
      "mint": "9oKmZmcftEUSKonPsKg3L3LNZSMeMTJNCXW5XGsSpump",
      "imageUrl": "https://cdn.dexscreener.com/cms/images/OiAeBs0aaQFPQ3Yu?width=800&height=800&quality=95&format=auto",
      "pumpFunUrl": "https://pump.fun/coin/9oKmZmcftEUSKonPsKg3L3LNZSMeMTJNCXW5XGsSpump",
      "fallbackUrl": "https://dexscreener.com/solana/9okmzmcfteuskonpskg3l3lnzsmemtjncxw5xgsspump",
      "label": "Low-cap discovery",
      "sourceName": "Public meme radar",
      "priceUsd": 0.00001575,
      "priceChange24h": -53.83,
      "marketCapUsd": 15755,
      "volume24hUsd": 546429.03,
      "lastUpdated": "2026-05-30T11:15:02.073Z",
      "sources": [
        "dexscreener"
      ],
      "confidence": 1
    },
    {
      "rank": 9,
      "name": "DONNY",
      "symbol": "DONNY",
      "mint": "G6BN4jNr83QkjGaSXtGJr2AJk5i3XgJotRHTvZCxpump",
      "imageUrl": "https://cdn.dexscreener.com/cms/images/JCw0eUf7oQiczqwr?width=800&height=800&quality=95&format=auto",
      "pumpFunUrl": "https://pump.fun/coin/G6BN4jNr83QkjGaSXtGJr2AJk5i3XgJotRHTvZCxpump",
      "fallbackUrl": "https://dexscreener.com/solana/g6bn4jnr83qkjgasxtgjr2ajk5i3xgjotrhtvzcxpump",
      "label": "Low-cap discovery",
      "sourceName": "Public meme radar",
      "priceUsd": 0.0001435,
      "priceChange24h": -41.88,
      "marketCapUsd": 136154,
      "volume24hUsd": 498561.73,
      "lastUpdated": "2026-05-30T11:15:02.073Z",
      "sources": [
        "dexscreener"
      ],
      "confidence": 1
    },
    {
      "rank": 10,
      "name": "Bubo",
      "symbol": "BUBO",
      "mint": "DZBff9C2LXgTSyy5WpG2UDzKSKVVYmi4vPjzdV9Spump",
      "imageUrl": "https://cdn.dexscreener.com/cms/images/zhgrtjQZYA9Z1EWo?width=800&height=800&quality=95&format=auto",
      "pumpFunUrl": "https://pump.fun/coin/DZBff9C2LXgTSyy5WpG2UDzKSKVVYmi4vPjzdV9Spump",
      "fallbackUrl": "https://dexscreener.com/solana/dzbff9c2lxgtsyy5wpg2udzkskvvymi4vpjzdv9spump",
      "label": "Low-cap discovery",
      "sourceName": "Public meme radar",
      "priceUsd": 0.00008511,
      "priceChange24h": 149,
      "marketCapUsd": 85113,
      "volume24hUsd": 461445.45,
      "lastUpdated": "2026-05-30T11:15:02.073Z",
      "sources": [
        "dexscreener",
        "gecko-terminal"
      ],
      "liquidityUsd": 22364.6288,
      "confidence": 2
    },
    {
      "rank": 11,
      "name": "Tay Story",
      "symbol": "TS",
      "mint": "BKCLq2Kcvk7ssjcj73w5HqN7U6zsZUDE8WEtpvTnpump",
      "imageUrl": "https://cdn.dexscreener.com/cms/images/xQSsasxP9Y_bVdJr?width=800&height=800&quality=95&format=auto",
      "pumpFunUrl": "https://pump.fun/coin/BKCLq2Kcvk7ssjcj73w5HqN7U6zsZUDE8WEtpvTnpump",
      "fallbackUrl": "https://dexscreener.com/solana/bkclq2kcvk7ssjcj73w5hqn7u6zszude8wetpvtnpump",
      "label": "Low-cap discovery",
      "sourceName": "Public meme radar",
      "priceUsd": 0.00003211,
      "priceChange24h": -6.12,
      "marketCapUsd": 32118,
      "volume24hUsd": 374458.38,
      "lastUpdated": "2026-05-30T11:15:02.073Z",
      "sources": [
        "dexscreener"
      ],
      "confidence": 1
    },
    {
      "rank": 12,
      "name": "Toylor Swift",
      "symbol": "Toylor",
      "mint": "D5erbncxYamGZmy5DzsVjQ1ybJbvGLsUJGFWrtzUpump",
      "imageUrl": "https://cdn.dexscreener.com/cms/images/Ei4UiWeZ2Qw0eqim?width=800&height=800&quality=95&format=auto",
      "pumpFunUrl": "https://pump.fun/coin/D5erbncxYamGZmy5DzsVjQ1ybJbvGLsUJGFWrtzUpump",
      "fallbackUrl": "https://dexscreener.com/solana/d5erbncxyamgzmy5dzsvjq1ybjbvglsujgfwrtzupump",
      "label": "Low-cap discovery",
      "sourceName": "Public meme radar",
      "priceUsd": 0.00004167,
      "priceChange24h": 21.97,
      "marketCapUsd": 41676,
      "volume24hUsd": 356238.84,
      "lastUpdated": "2026-05-30T11:15:02.073Z",
      "sources": [
        "dexscreener"
      ],
      "confidence": 1
    },
    {
      "rank": 13,
      "name": "Pokesol MMO",
      "symbol": "POKERITE",
      "mint": "FPjywWb7oMGg4owWWEVb4fDvM79hDDEF52c6m2eMpump",
      "imageUrl": "https://cdn.dexscreener.com/cms/images/2mWIz8Nz3PnKSO5h?width=800&height=800&quality=95&format=auto",
      "pumpFunUrl": "https://pump.fun/coin/FPjywWb7oMGg4owWWEVb4fDvM79hDDEF52c6m2eMpump",
      "fallbackUrl": "https://dexscreener.com/solana/fpjywwb7omgg4owwwevb4fdvm79hddef52c6m2empump",
      "label": "Low-cap discovery",
      "sourceName": "Public meme radar",
      "priceUsd": 0.00002269,
      "priceChange24h": -31.1,
      "marketCapUsd": 22222,
      "volume24hUsd": 192445.16,
      "lastUpdated": "2026-05-30T11:15:02.073Z",
      "sources": [
        "dexscreener"
      ],
      "confidence": 1
    },
    {
      "rank": 14,
      "name": "Kätalyst",
      "symbol": "Kätalyst",
      "mint": "7XujDi97puebmckBPsrSAYg44epkuwm2qT5TND1Xpump",
      "imageUrl": "https://cdn.dexscreener.com/cms/images/AdRckHmK-0pAbRp5?width=800&height=800&quality=95&format=auto",
      "pumpFunUrl": "https://pump.fun/coin/7XujDi97puebmckBPsrSAYg44epkuwm2qT5TND1Xpump",
      "fallbackUrl": "https://dexscreener.com/solana/7xujdi97puebmckbpsrsayg44epkuwm2qt5tnd1xpump",
      "label": "Low-cap discovery",
      "sourceName": "Public meme radar",
      "priceUsd": 0.00001272,
      "priceChange24h": 356,
      "marketCapUsd": 12721.41,
      "volume24hUsd": 141794.78,
      "lastUpdated": "2026-05-30T11:15:02.073Z",
      "sources": [
        "dexscreener"
      ],
      "confidence": 1
    },
    {
      "rank": 15,
      "name": "The Mouse As Big As The Elephant",
      "symbol": "🐁 🐘",
      "mint": "4pXLCBkbq98KmdSxQhG3UHPDvhRPx76XbSD7zAQSpump",
      "imageUrl": "https://cdn.dexscreener.com/cms/images/SnBOq6wcuwJ3rtUf?width=800&height=800&quality=95&format=auto",
      "pumpFunUrl": "https://pump.fun/coin/4pXLCBkbq98KmdSxQhG3UHPDvhRPx76XbSD7zAQSpump",
      "fallbackUrl": "https://dexscreener.com/solana/4pxlcbkbq98kmdsxqhg3uhpdvhrpx76xbsd7zaqspump",
      "label": "Low-cap discovery",
      "sourceName": "Public meme radar",
      "priceUsd": 0.000009264,
      "priceChange24h": 233,
      "marketCapUsd": 9264.11,
      "volume24hUsd": 106551.68,
      "lastUpdated": "2026-05-30T11:15:02.073Z",
      "sources": [
        "dexscreener"
      ],
      "confidence": 1
    },
    {
      "rank": 16,
      "name": "The Rally Rabbit",
      "symbol": "Rally",
      "mint": "5UErAnwSnGBPRkhxSjKiswMemr1uipvMPHLFfZrDpump",
      "imageUrl": "https://cdn.dexscreener.com/cms/images/1bFV3QCdHTS2_13R?width=800&height=800&quality=95&format=auto",
      "pumpFunUrl": "https://pump.fun/coin/5UErAnwSnGBPRkhxSjKiswMemr1uipvMPHLFfZrDpump",
      "fallbackUrl": "https://dexscreener.com/solana/5ueranwsngbprkhxsjkiswmemr1uipvmphlffzrdpump",
      "label": "Low-cap discovery",
      "sourceName": "Public meme radar",
      "priceUsd": 0.00001222,
      "priceChange24h": 250,
      "marketCapUsd": 12220.67,
      "volume24hUsd": 87516.88,
      "lastUpdated": "2026-05-30T11:15:02.073Z",
      "sources": [
        "dexscreener"
      ],
      "confidence": 1
    },
    {
      "rank": 17,
      "name": "SpaceExplorationTechnologiesCorp",
      "symbol": "SPCX",
      "mint": "26YRpwvWhTSBSAkQbhNP6AXBNrJe8uRxibAn7ZXXpump",
      "imageUrl": "https://cdn.dexscreener.com/cms/images/etlEYrLXlwugk3S0?width=800&height=800&quality=95&format=auto",
      "pumpFunUrl": "https://pump.fun/coin/26YRpwvWhTSBSAkQbhNP6AXBNrJe8uRxibAn7ZXXpump",
      "fallbackUrl": "https://dexscreener.com/solana/26yrpwvwhtsbsakqbhnp6axbnrje8urxiban7zxxpump",
      "label": "Low-cap discovery",
      "sourceName": "Public meme radar",
      "priceUsd": 0.0003847,
      "priceChange24h": 19.87,
      "marketCapUsd": 382504,
      "volume24hUsd": 84268.99,
      "lastUpdated": "2026-05-30T11:15:02.073Z",
      "sources": [
        "dexscreener"
      ],
      "confidence": 1
    },
    {
      "rank": 18,
      "name": "Oklahoma City Thunder",
      "symbol": "OKC",
      "mint": "GQASup5cYyHupWSvGMhQy4Gm79wFPWPg9D3oUmppump",
      "imageUrl": "https://cdn.dexscreener.com/cms/images/rqxazkmygFI3NcaF?width=800&height=800&quality=95&format=auto",
      "pumpFunUrl": "https://pump.fun/coin/GQASup5cYyHupWSvGMhQy4Gm79wFPWPg9D3oUmppump",
      "fallbackUrl": "https://dexscreener.com/solana/gqasup5cyyhupwsvgmhqy4gm79wfpwpg9d3oumppump",
      "label": "Low-cap discovery",
      "sourceName": "Public meme radar",
      "priceUsd": 0.00001437,
      "priceChange24h": 360,
      "marketCapUsd": 14373.15,
      "volume24hUsd": 82746.15,
      "lastUpdated": "2026-05-30T11:15:02.073Z",
      "sources": [
        "dexscreener"
      ],
      "confidence": 1
    },
    {
      "rank": 19,
      "name": "AIRDROP",
      "symbol": "AIR",
      "mint": "3J87uiVnxuVhg5Air2KLKPEJbc93ppNq6cnAFzqBpump",
      "imageUrl": "https://cdn.dexscreener.com/cms/images/vsJ08nNG5mYFiHjd?width=800&height=800&quality=95&format=auto",
      "pumpFunUrl": "https://pump.fun/coin/3J87uiVnxuVhg5Air2KLKPEJbc93ppNq6cnAFzqBpump",
      "fallbackUrl": "https://dexscreener.com/solana/3j87uivnxuvhg5air2klkpejbc93ppnq6cnafzqbpump",
      "label": "Low-cap discovery",
      "sourceName": "Public meme radar",
      "priceUsd": 0.00001907,
      "priceChange24h": -44.32,
      "marketCapUsd": 19078,
      "volume24hUsd": 72790.92,
      "lastUpdated": "2026-05-30T11:15:02.073Z",
      "sources": [
        "dexscreener"
      ],
      "confidence": 1
    },
    {
      "rank": 20,
      "name": "New Elon Dog",
      "symbol": "CALI",
      "mint": "7BGXDFP9FLdK8bLmGyV7BdvvkdN1QTdDPsap4pztpump",
      "imageUrl": "https://cdn.dexscreener.com/cms/images/CAzAhB8a85fU19E-?width=800&height=800&quality=95&format=auto",
      "pumpFunUrl": "https://pump.fun/coin/7BGXDFP9FLdK8bLmGyV7BdvvkdN1QTdDPsap4pztpump",
      "fallbackUrl": "https://dexscreener.com/solana/7bgxdfp9fldk8blmgyv7bdvvkdn1qtddpsap4pztpump",
      "label": "Low-cap discovery",
      "sourceName": "Public meme radar",
      "priceUsd": 0.000004582,
      "priceChange24h": 100,
      "marketCapUsd": 4582.36,
      "volume24hUsd": 67803.21,
      "lastUpdated": "2026-05-30T11:15:02.073Z",
      "sources": [
        "dexscreener"
      ],
      "confidence": 1
    },
    {
      "rank": 21,
      "name": "drooling patrick",
      "symbol": "pawtrick",
      "mint": "BPZ86XqH5Ch1r9NokAQzEicogaFyEqDM5WE4UnEbpump",
      "imageUrl": "https://cdn.dexscreener.com/cms/images/s2I9r3T7UdWtM74_?width=800&height=800&quality=95&format=auto",
      "pumpFunUrl": "https://pump.fun/coin/BPZ86XqH5Ch1r9NokAQzEicogaFyEqDM5WE4UnEbpump",
      "fallbackUrl": "https://dexscreener.com/solana/bpz86xqh5ch1r9nokaqzeicogafyeqdm5we4unebpump",
      "label": "Low-cap discovery",
      "sourceName": "Public meme radar",
      "priceUsd": 0.00000728,
      "priceChange24h": -44.25,
      "marketCapUsd": 7280.34,
      "volume24hUsd": 54256.67,
      "lastUpdated": "2026-05-30T11:15:02.073Z",
      "sources": [
        "dexscreener"
      ],
      "confidence": 1
    },
    {
      "rank": 22,
      "name": "The Last X Community",
      "symbol": "Community",
      "mint": "8dqQtM7eDQeamYMRnQw5dSV73byyKkogLuMKz3ykpump",
      "imageUrl": "https://cdn.dexscreener.com/cms/images/H56z0zy4JB6lhJ1K?width=800&height=800&quality=95&format=auto",
      "pumpFunUrl": "https://pump.fun/coin/8dqQtM7eDQeamYMRnQw5dSV73byyKkogLuMKz3ykpump",
      "fallbackUrl": "https://dexscreener.com/solana/8dqqtm7edqeamymrnqw5dsv73byykkoglumkz3ykpump",
      "label": "Low-cap discovery",
      "sourceName": "Public meme radar",
      "priceUsd": 0.00001511,
      "priceChange24h": 496,
      "marketCapUsd": 15117.87,
      "volume24hUsd": 52374.26,
      "lastUpdated": "2026-05-30T11:15:02.073Z",
      "sources": [
        "dexscreener"
      ],
      "confidence": 1
    },
    {
      "rank": 23,
      "name": "International Peacekeepers Day",
      "symbol": "PEACE",
      "mint": "DKcM5RYqjqT3jSFQKQPJkZYjMxk7WmBJvwKamNDvpump",
      "imageUrl": "https://cdn.dexscreener.com/cms/images/UmjiFjGrJp5gPQes?width=800&height=800&quality=95&format=auto",
      "pumpFunUrl": "https://pump.fun/coin/DKcM5RYqjqT3jSFQKQPJkZYjMxk7WmBJvwKamNDvpump",
      "fallbackUrl": "https://dexscreener.com/solana/dkcm5ryqjqt3jsfqkqpjkzyjmxk7wmbjvwkamndvpump",
      "label": "Low-cap discovery",
      "sourceName": "Public meme radar",
      "priceUsd": 0.000002164,
      "priceChange24h": -93.41,
      "marketCapUsd": 2030,
      "volume24hUsd": 51173.22,
      "lastUpdated": "2026-05-30T11:15:02.073Z",
      "sources": [
        "dexscreener"
      ],
      "confidence": 1
    },
    {
      "rank": 24,
      "name": "Privacy Coin",
      "symbol": "PRIVACY",
      "mint": "5U4p7CF1XkWTTEuCH2Dh4FbixPabK3H7abCdzL2tpump",
      "imageUrl": "https://cdn.dexscreener.com/cms/images/oU3Av3pb3ETATS5U?width=800&height=800&quality=95&format=auto",
      "pumpFunUrl": "https://pump.fun/coin/5U4p7CF1XkWTTEuCH2Dh4FbixPabK3H7abCdzL2tpump",
      "fallbackUrl": "https://dexscreener.com/solana/5u4p7cf1xkwtteuch2dh4fbixpabk3h7abcdzl2tpump",
      "label": "Low-cap discovery",
      "sourceName": "Public meme radar",
      "priceUsd": 0.00003278,
      "priceChange24h": -3.33,
      "marketCapUsd": 32786,
      "volume24hUsd": 35542.27,
      "lastUpdated": "2026-05-30T11:15:02.073Z",
      "sources": [
        "dexscreener"
      ],
      "confidence": 1
    },
    {
      "rank": 25,
      "name": "The Eternal Dog",
      "symbol": "Hachiko",
      "mint": "CJuAc61eawmEmfJ4XjgKUTPQ2uNZXxLnMmMXqxQUpump",
      "imageUrl": "https://cdn.dexscreener.com/cms/images/L3rXmA3VDFpZ_Q_3?width=800&height=800&quality=95&format=auto",
      "pumpFunUrl": "https://pump.fun/coin/CJuAc61eawmEmfJ4XjgKUTPQ2uNZXxLnMmMXqxQUpump",
      "fallbackUrl": "https://dexscreener.com/solana/cjuac61eawmemfj4xjgkutpq2unzxxlnmmmxqxqupump",
      "label": "Low-cap discovery",
      "sourceName": "Public meme radar",
      "priceUsd": 0.000008448,
      "priceChange24h": 224,
      "marketCapUsd": 8448.46,
      "volume24hUsd": 34531.64,
      "lastUpdated": "2026-05-30T11:15:02.073Z",
      "sources": [
        "dexscreener"
      ],
      "confidence": 1
    },
    {
      "rank": 26,
      "name": "genny.tech",
      "symbol": "GENNY",
      "mint": "BkCVgVcKS1u5j18w9Gt2P4vA2ws5DLRGmJkzfkUJpump",
      "imageUrl": "https://cdn.dexscreener.com/cms/images/gY-Q8wtBVkD9JJh8?width=800&height=800&quality=95&format=auto",
      "pumpFunUrl": "https://pump.fun/coin/BkCVgVcKS1u5j18w9Gt2P4vA2ws5DLRGmJkzfkUJpump",
      "fallbackUrl": "https://dexscreener.com/solana/bkcvgvcks1u5j18w9gt2p4va2ws5dlrgmjkzfkujpump",
      "label": "Low-cap discovery",
      "sourceName": "Public meme radar",
      "priceUsd": 0.0000231,
      "priceChange24h": 889,
      "marketCapUsd": 23101.08,
      "volume24hUsd": 29226.11,
      "lastUpdated": "2026-05-30T11:15:02.073Z",
      "sources": [
        "dexscreener"
      ],
      "confidence": 1
    },
    {
      "rank": 27,
      "name": "The Company",
      "symbol": "COMPANY",
      "mint": "8fuoMSAMxPXCYGq3h7GTfGYxsaULghVuz5jPHXoTpump",
      "imageUrl": "https://cdn.dexscreener.com/cms/images/VFg-mbOZU57aPwVm?width=800&height=800&quality=95&format=auto",
      "pumpFunUrl": "https://pump.fun/coin/8fuoMSAMxPXCYGq3h7GTfGYxsaULghVuz5jPHXoTpump",
      "fallbackUrl": "https://dexscreener.com/solana/8fuomsamxpxcygq3h7gtfgyxsaulghvuz5jphxotpump",
      "label": "Low-cap discovery",
      "sourceName": "Public meme radar",
      "priceUsd": 0.000009437,
      "priceChange24h": 272,
      "marketCapUsd": 9437.02,
      "volume24hUsd": 13271.87,
      "lastUpdated": "2026-05-30T11:15:02.073Z",
      "sources": [
        "dexscreener"
      ],
      "confidence": 1
    },
    {
      "rank": 28,
      "name": "Mad Coin",
      "symbol": "MAD",
      "mint": "Fa7ZE9nCEYnrHsnoeHuhEExJpchtrBtKXnWe6CgHpump",
      "imageUrl": "https://cdn.dexscreener.com/cms/images/fe40b5b45fba5474c9255d37f76846b0e0e8aee5436a483d8f8df0ea234fd99b?width=800&height=800&quality=95&format=auto",
      "pumpFunUrl": "https://pump.fun/coin/Fa7ZE9nCEYnrHsnoeHuhEExJpchtrBtKXnWe6CgHpump",
      "fallbackUrl": "https://dexscreener.com/solana/fa7ze9nceynrhsnoehuheexjpchtrbtkxnwe6cghpump",
      "label": "Low-cap discovery",
      "sourceName": "Public meme radar",
      "priceUsd": 0.000393,
      "priceChange24h": 1.52,
      "marketCapUsd": 196511,
      "volume24hUsd": 12860.42,
      "lastUpdated": "2026-05-30T11:15:02.073Z",
      "sources": [
        "dexscreener"
      ],
      "confidence": 1
    },
    {
      "rank": 29,
      "name": "PRIDE TROLL",
      "symbol": "PRIDETROLL",
      "mint": "APDCqK5jpSR2YjNxTH6dKJzFwvGcjdQx5kPevU2gpump",
      "imageUrl": "https://cdn.dexscreener.com/cms/images/M_kIBg8LDYeAIzi2?width=800&height=800&quality=95&format=auto",
      "pumpFunUrl": "https://pump.fun/coin/APDCqK5jpSR2YjNxTH6dKJzFwvGcjdQx5kPevU2gpump",
      "fallbackUrl": "https://dexscreener.com/solana/apdcqk5jpsr2yjnxth6dkjzfwvgcjdqx5kpevu2gpump",
      "label": "Low-cap discovery",
      "sourceName": "Public meme radar",
      "priceUsd": 0.000008763,
      "priceChange24h": 209,
      "marketCapUsd": 8763.31,
      "volume24hUsd": 10710.13,
      "lastUpdated": "2026-05-30T11:15:02.073Z",
      "sources": [
        "dexscreener"
      ],
      "confidence": 1
    }
  ]
}
