{
  "schemaVersion": 3,
  "updatedAt": "2026-05-25T08:15:03.763Z",
  "source": {
    "primaryAttempt": "Pump.fun frontend API",
    "active": "DexScreener public API fallback",
    "endpoint": "https://api.dexscreener.com/token-boosts/top/v1",
    "blocker": "Pump.fun frontend API returned 403 and redirected/blocked non-browser fetches.",
    "providers": [
      "DexScreener public API fallback",
      "GeckoTerminal Solana trending pools",
      "CoinGecko solana-meme-coins",
      "Raydium top-liquidity pools (70)",
      "Jupiter /swap/v1/quote (tradability)"
    ],
    "poolSize": 105,
    "schema": "dailyRadar/trending/highCap/lowCap + per-row sources[]+confidence"
  },
  "dailyRadar": [
    {
      "rank": 1,
      "name": "Paladin Trump AI",
      "symbol": "PTAI",
      "mint": "2SAt9qF6YjMBz9tb1U9jAYNBBVx5jqWQ7KRXDqD2pump",
      "imageUrl": "https://cdn.dexscreener.com/cms/images/_cEDICWwmcBO3zQA?width=800&height=800&quality=95&format=auto",
      "pumpFunUrl": "https://pump.fun/coin/2SAt9qF6YjMBz9tb1U9jAYNBBVx5jqWQ7KRXDqD2pump",
      "fallbackUrl": "https://dexscreener.com/solana/2sat9qf6yjmbz9tb1u9jaynbbvx5jqwq7krxdqd2pump",
      "label": "Daily Radar pick",
      "sourceName": "Public meme radar",
      "priceUsd": 0.0009884,
      "priceChange24h": 5301,
      "marketCapUsd": 986877,
      "volume24hUsd": 554460.61,
      "lastUpdated": "2026-05-25T08:15:02.499Z",
      "sources": [
        "dexscreener"
      ],
      "confidence": 1,
      "momentumScore": 2652.548,
      "tradable": true
    },
    {
      "rank": 2,
      "name": "Staked Bank",
      "symbol": "STAKE",
      "mint": "5s7tf6ih2CEZf7ZPNkJAtcknAq9DL5GsWHMMT3Jdpump",
      "imageUrl": "https://assets.geckoterminal.com/54s7dzymnxdy9db1q2xlg6bnxgao",
      "pumpFunUrl": "https://pump.fun/coin/5s7tf6ih2CEZf7ZPNkJAtcknAq9DL5GsWHMMT3Jdpump",
      "fallbackUrl": "https://www.geckoterminal.com/solana/pools/EyUhvULaCx9N1a3mj4LZTs6ju7Ejk49sFmtjNe65MPNv",
      "label": "Daily Radar pick",
      "sourceName": "GeckoTerminal",
      "priceUsd": 0.0009628143283291039,
      "priceChange24h": 958.598,
      "marketCapUsd": 962932.4178,
      "volume24hUsd": 7014311.23320361,
      "liquidityUsd": 91524.17,
      "lastUpdated": "2026-05-25T08:15:03.080Z",
      "sources": [
        "gecko-terminal"
      ],
      "confidence": 1,
      "momentumScore": 482.31,
      "tradable": true
    },
    {
      "rank": 3,
      "name": "CLASH RPG",
      "symbol": "RPG",
      "mint": "DKT5XA8Tcas6xZ7pqLGFghVETjRMWxCJDxMJGXM3pump",
      "imageUrl": "https://cdn.dexscreener.com/cms/images/kz3HCq4ACp_sUee8?width=800&height=800&quality=95&format=auto",
      "pumpFunUrl": "https://pump.fun/coin/DKT5XA8Tcas6xZ7pqLGFghVETjRMWxCJDxMJGXM3pump",
      "fallbackUrl": "https://dexscreener.com/solana/dkt5xa8tcas6xz7pqlgfghvetjrmwxcjdxmjgxm3pump",
      "label": "Daily Radar pick",
      "sourceName": "Public meme radar",
      "priceUsd": 0.00002256,
      "priceChange24h": 809,
      "marketCapUsd": 22568.28,
      "volume24hUsd": 45774.89,
      "lastUpdated": "2026-05-25T08:15:02.500Z",
      "sources": [
        "dexscreener"
      ],
      "confidence": 1,
      "momentumScore": 406.085,
      "tradable": true
    }
  ],
  "trending": [
    {
      "rank": 1,
      "name": "Paraloom",
      "symbol": "PARALOOM",
      "mint": "Br1JxELQYP34YdRW4gbEPLasHEtyz8eCmT2FvmnYpump",
      "imageUrl": "https://assets.geckoterminal.com/vjdjymhy6yyx0j44xhkjxsojozhu",
      "pumpFunUrl": "https://pump.fun/coin/Br1JxELQYP34YdRW4gbEPLasHEtyz8eCmT2FvmnYpump",
      "fallbackUrl": "https://www.geckoterminal.com/solana/pools/9ekUjhCnJDzqW5QXk41jeKjteUdHquK5DJh8mRDHtqA7",
      "label": "GeckoTerminal trending pool",
      "sourceName": "GeckoTerminal",
      "priceUsd": 0.0004593178780395924,
      "priceChange24h": 691.713,
      "marketCapUsd": 466001.9803,
      "volume24hUsd": 1816988.55433654,
      "liquidityUsd": 72549.799,
      "lastUpdated": "2026-05-25T08:15:03.080Z",
      "sources": [
        "gecko-terminal"
      ],
      "confidence": 1
    },
    {
      "rank": 2,
      "name": "Heknitt The Frog",
      "symbol": "Heknitt",
      "mint": "AsCHop6RyD46GuYN3T7zhT1KBRqMe5dUxCbkrqUNpump",
      "imageUrl": "https://cdn.dexscreener.com/cms/images/DMqFxUOZNusx71J2?width=800&height=800&quality=95&format=auto",
      "pumpFunUrl": "https://pump.fun/coin/AsCHop6RyD46GuYN3T7zhT1KBRqMe5dUxCbkrqUNpump",
      "fallbackUrl": "https://dexscreener.com/solana/aschop6ryd46guyn3t7zht1kbrqme5duxcbkrqunpump",
      "label": "High-cap Pump.fun coin",
      "sourceName": "Public meme radar",
      "priceUsd": 0.00001902,
      "priceChange24h": 610,
      "marketCapUsd": 19021.07,
      "volume24hUsd": 83184.64,
      "lastUpdated": "2026-05-25T08:15:02.500Z",
      "sources": [
        "dexscreener"
      ],
      "confidence": 1
    },
    {
      "rank": 3,
      "name": "cig",
      "symbol": "CIG",
      "mint": "cig9AXeEzQMUts9WXzmb8S5DapSVJ2b8JnrRmnWRdYz",
      "imageUrl": "https://assets.geckoterminal.com/98dpjh73cirm2pbowg9i6ze6jxjh",
      "pumpFunUrl": "",
      "fallbackUrl": "https://www.geckoterminal.com/solana/pools/B5ihVH6qRkGTXhp61MZG5rRAmaCwtva3P2gRbZZrFU65",
      "label": "GeckoTerminal trending pool",
      "sourceName": "GeckoTerminal",
      "priceUsd": 0.00023722916482144335,
      "priceChange24h": 605.264,
      "marketCapUsd": 242378.7871,
      "volume24hUsd": 651731.221741954,
      "liquidityUsd": 40546.812,
      "lastUpdated": "2026-05-25T08:15:03.080Z",
      "sources": [
        "gecko-terminal"
      ],
      "confidence": 1
    },
    {
      "rank": 4,
      "name": "Froggies",
      "symbol": "Froggies",
      "mint": "9BTMgdUJtjvRyyXQZwAaP4v3C5tVCbd9EQXEwgP1pump",
      "imageUrl": "https://cdn.dexscreener.com/cms/images/Ax3jq3F5rEFXvZuh?width=800&height=800&quality=95&format=auto",
      "pumpFunUrl": "https://pump.fun/coin/9BTMgdUJtjvRyyXQZwAaP4v3C5tVCbd9EQXEwgP1pump",
      "fallbackUrl": "https://dexscreener.com/solana/9btmgdujtjvryyxqzwaap4v3c5tvcbd9eqxewgp1pump",
      "label": "High-cap Pump.fun coin",
      "sourceName": "Public meme radar",
      "priceUsd": 0.00001569,
      "priceChange24h": 546,
      "marketCapUsd": 15693.83,
      "volume24hUsd": 61031.04,
      "lastUpdated": "2026-05-25T08:15:02.500Z",
      "sources": [
        "dexscreener"
      ],
      "confidence": 1
    },
    {
      "rank": 5,
      "name": "The Infinite Runner",
      "symbol": "Cameraman",
      "mint": "8zbDMAYmR7pZnLahQDUctPbPsqeADU1D9BuA9Kpnpump",
      "imageUrl": "https://cdn.dexscreener.com/cms/images/JBegRwnzNx6kqzSl?width=800&height=800&quality=95&format=auto",
      "pumpFunUrl": "https://pump.fun/coin/8zbDMAYmR7pZnLahQDUctPbPsqeADU1D9BuA9Kpnpump",
      "fallbackUrl": "https://dexscreener.com/solana/8zbdmaymr7pznlahqductpbpsqeadu1d9bua9kpnpump",
      "label": "High-cap Pump.fun coin",
      "sourceName": "Public meme radar",
      "priceUsd": 0.00002442,
      "priceChange24h": 425,
      "marketCapUsd": 24424.34,
      "volume24hUsd": 58046.87,
      "lastUpdated": "2026-05-25T08:15:02.500Z",
      "sources": [
        "dexscreener"
      ],
      "confidence": 1
    },
    {
      "rank": 6,
      "name": "DICKMAXXING",
      "symbol": "DICKMAXX",
      "mint": "E1cdRMCYqEWE8xKxmEFmTxv6FbsfA4sK6SxCq8Rzpump",
      "imageUrl": "https://cdn.dexscreener.com/cms/images/naNmVOe-RrWg-Abp?width=800&height=800&quality=95&format=auto",
      "pumpFunUrl": "https://pump.fun/coin/E1cdRMCYqEWE8xKxmEFmTxv6FbsfA4sK6SxCq8Rzpump",
      "fallbackUrl": "https://dexscreener.com/solana/e1cdrmcyqewe8xkxmefmtxv6fbsfa4sk6sxcq8rzpump",
      "label": "Boosted Pump.fun coin",
      "sourceName": "Public meme radar",
      "priceUsd": 0.0001769,
      "priceChange24h": 404,
      "marketCapUsd": 176953,
      "volume24hUsd": 801077.73,
      "lastUpdated": "2026-05-25T08:15:02.499Z",
      "sources": [
        "dexscreener"
      ],
      "confidence": 1
    },
    {
      "rank": 7,
      "name": "endless twap bid",
      "symbol": "ETB",
      "mint": "Cjo46uRW2yeF2uXLn2phrVZZyZ1sfnrMNutfrhZopump",
      "imageUrl": "https://assets.geckoterminal.com/kmlkw4xhuglgurld6zvmn9hql2bc",
      "pumpFunUrl": "https://pump.fun/coin/Cjo46uRW2yeF2uXLn2phrVZZyZ1sfnrMNutfrhZopump",
      "fallbackUrl": "https://www.geckoterminal.com/solana/pools/FMT7qeayftbQteCWbNmZWmHpEojjVzLBLtfkFUHWRP8h",
      "label": "GeckoTerminal trending pool",
      "sourceName": "GeckoTerminal",
      "priceUsd": 0.00011147118564953024,
      "priceChange24h": 293.69,
      "marketCapUsd": 111471.1856,
      "volume24hUsd": 2148658.71118325,
      "liquidityUsd": 29089.0712,
      "lastUpdated": "2026-05-25T08:15:03.080Z",
      "sources": [
        "gecko-terminal"
      ],
      "confidence": 1
    },
    {
      "rank": 8,
      "name": "King of The Hill",
      "symbol": "KOTH",
      "mint": "G6DB3YRxNyBrMwNzsrBdZ3n4fuV3bJb8qHNAhpz8pump",
      "imageUrl": "https://cdn.dexscreener.com/cms/images/tG7OZ6hOhaTn_7mR?width=800&height=800&quality=95&format=auto",
      "pumpFunUrl": "https://pump.fun/coin/G6DB3YRxNyBrMwNzsrBdZ3n4fuV3bJb8qHNAhpz8pump",
      "fallbackUrl": "https://dexscreener.com/solana/g6db3yrxnybrmwnzsrbdz3n4fuv3bjb8qhnahpz8pump",
      "label": "High-cap Pump.fun coin",
      "sourceName": "Public meme radar",
      "priceUsd": 0.00001268,
      "priceChange24h": 227,
      "marketCapUsd": 12681.61,
      "volume24hUsd": 75748.17,
      "lastUpdated": "2026-05-25T08:15:02.500Z",
      "sources": [
        "dexscreener"
      ],
      "confidence": 1
    },
    {
      "rank": 9,
      "name": "Generational Wealth",
      "symbol": "GENWEALTH",
      "mint": "5gdkymiHDBetTnCBjr1YAeqMCeGJKVFRkumrAAgmpump",
      "imageUrl": "https://cdn.dexscreener.com/cms/images/_ZL__q7tb0MwO2Lu?width=800&height=800&quality=95&format=auto",
      "pumpFunUrl": "https://pump.fun/coin/5gdkymiHDBetTnCBjr1YAeqMCeGJKVFRkumrAAgmpump",
      "fallbackUrl": "https://dexscreener.com/solana/5gdkymihdbettncbjr1yaeqmcegjkvfrkumraagmpump",
      "label": "Boosted Pump.fun coin",
      "sourceName": "Public meme radar",
      "priceUsd": 0.0001173,
      "priceChange24h": 219,
      "marketCapUsd": 117396,
      "volume24hUsd": 693580.69,
      "lastUpdated": "2026-05-25T08:15:02.499Z",
      "sources": [
        "dexscreener",
        "gecko-terminal"
      ],
      "liquidityUsd": 28338.4423,
      "confidence": 2
    },
    {
      "rank": 10,
      "name": "Troll Cup",
      "symbol": "TROLL CUP",
      "mint": "67nDo3T2wGSS6SvBa64y3ASUrqvVwReVkhnnJJ39pump",
      "imageUrl": "https://cdn.dexscreener.com/cms/images/oJV_dmdxcj-JloJf?width=800&height=800&quality=95&format=auto",
      "pumpFunUrl": "https://pump.fun/coin/67nDo3T2wGSS6SvBa64y3ASUrqvVwReVkhnnJJ39pump",
      "fallbackUrl": "https://dexscreener.com/solana/67ndo3t2wgss6svba64y3asurqvvwrevkhnnjj39pump",
      "label": "Boosted Pump.fun coin",
      "sourceName": "Public meme radar",
      "priceUsd": 0.0001113,
      "priceChange24h": 214,
      "marketCapUsd": 111379,
      "volume24hUsd": 190256.54,
      "lastUpdated": "2026-05-25T08:15:02.499Z",
      "sources": [
        "dexscreener"
      ],
      "confidence": 1
    },
    {
      "rank": 11,
      "name": "forg",
      "symbol": "FORG",
      "mint": "7NeQaB9aSU4iTKyv9onCp9RUPY4pj33ecacX6AKLpump",
      "imageUrl": "https://cdn.dexscreener.com/cms/images/x3Rn4V40QthZfeSW?width=800&height=800&quality=95&format=auto",
      "pumpFunUrl": "https://pump.fun/coin/7NeQaB9aSU4iTKyv9onCp9RUPY4pj33ecacX6AKLpump",
      "fallbackUrl": "https://dexscreener.com/solana/7neqab9asu4itkyv9oncp9rupy4pj33ecacx6aklpump",
      "label": "High-cap Pump.fun coin",
      "sourceName": "Public meme radar",
      "priceUsd": 0.000007824,
      "priceChange24h": 196,
      "marketCapUsd": 7824.99,
      "volume24hUsd": 109364.45,
      "lastUpdated": "2026-05-25T08:15:02.500Z",
      "sources": [
        "dexscreener"
      ],
      "confidence": 1
    },
    {
      "rank": 12,
      "name": "Tralalero Tralala",
      "symbol": "TRALALERO",
      "mint": "2MBq3mrKSKf6NnG5x29rBK4B9f7CWR4N1EQJ18NsViRL",
      "imageUrl": "https://assets.geckoterminal.com/bfw4or07u53g4pozt4dar9qu9n9q",
      "pumpFunUrl": "",
      "fallbackUrl": "https://www.geckoterminal.com/solana/pools/EH29xSBPYuTBCkCpnXtcWGyveiSf56AsTTd8BgBNhoBa",
      "label": "GeckoTerminal trending pool",
      "sourceName": "GeckoTerminal",
      "priceUsd": 0.0005123489336648536,
      "priceChange24h": 148.387,
      "marketCapUsd": 512348.9337,
      "volume24hUsd": 2308236.09620478,
      "liquidityUsd": 78787.3743,
      "lastUpdated": "2026-05-25T08:15:03.080Z",
      "sources": [
        "gecko-terminal"
      ],
      "confidence": 1
    },
    {
      "rank": 13,
      "name": "Affirm",
      "symbol": "AFFIRM",
      "mint": "6upR4PbZwdHrY6TfJpeygUoQMEkmLMdStoBQqimTpump",
      "imageUrl": "https://cdn.dexscreener.com/cms/images/pGA3mRIMYkcHf4AL?width=800&height=800&quality=95&format=auto",
      "pumpFunUrl": "https://pump.fun/coin/6upR4PbZwdHrY6TfJpeygUoQMEkmLMdStoBQqimTpump",
      "fallbackUrl": "https://dexscreener.com/solana/6upr4pbzwdhry6tfjpeyguoqmekmlmdstobqqimtpump",
      "label": "High-cap Pump.fun coin",
      "sourceName": "Public meme radar",
      "priceUsd": 0.0000859,
      "priceChange24h": 143,
      "marketCapUsd": 85906,
      "volume24hUsd": 346443.07,
      "lastUpdated": "2026-05-25T08:15:02.500Z",
      "sources": [
        "dexscreener"
      ],
      "confidence": 1
    },
    {
      "rank": 14,
      "name": "BELIEF",
      "symbol": "BELIEF",
      "mint": "5N8zivsMVY13XRnUrqkvS46qf48S6iw4rHB7wjhcpump",
      "imageUrl": "https://assets.geckoterminal.com/zfd8hzds7dw6ojnf138ahqcx620k",
      "pumpFunUrl": "https://pump.fun/coin/5N8zivsMVY13XRnUrqkvS46qf48S6iw4rHB7wjhcpump",
      "fallbackUrl": "https://www.geckoterminal.com/solana/pools/4L29chFWwQ2HC6ZBB7Zr5otKaCQ85rme9tsQ9tioAimm",
      "label": "GeckoTerminal trending pool",
      "sourceName": "GeckoTerminal",
      "priceUsd": 0.00006955592895973572,
      "priceChange24h": 91.814,
      "marketCapUsd": 68633.98765,
      "volume24hUsd": 1468607.53222998,
      "liquidityUsd": 22460.6082,
      "lastUpdated": "2026-05-25T08:15:03.080Z",
      "sources": [
        "gecko-terminal"
      ],
      "confidence": 1
    },
    {
      "rank": 15,
      "name": "America is Rich",
      "symbol": "RICHAMERICA",
      "mint": "CLvqTFi16ptkhFLJjZdHyVjouef8aPaqugjYGhURpump",
      "imageUrl": "https://cdn.dexscreener.com/cms/images/LlswItNeE0EFePuV?width=800&height=800&quality=95&format=auto",
      "pumpFunUrl": "https://pump.fun/coin/CLvqTFi16ptkhFLJjZdHyVjouef8aPaqugjYGhURpump",
      "fallbackUrl": "https://dexscreener.com/solana/clvqtfi16ptkhfljjzdhyvjouef8apaqugjyghurpump",
      "label": "Boosted Pump.fun coin",
      "sourceName": "Public meme radar",
      "priceUsd": 0.0001903,
      "priceChange24h": 83.47,
      "marketCapUsd": 190350,
      "volume24hUsd": 983502.7,
      "lastUpdated": "2026-05-25T08:15:02.499Z",
      "sources": [
        "dexscreener"
      ],
      "confidence": 1
    },
    {
      "rank": 16,
      "name": "Memehood",
      "symbol": "MHOOD",
      "mint": "2xan3NB3HWAD1QzGwKjjP629BxpCykB9nH1kGGF1pump",
      "imageUrl": "https://cdn.dexscreener.com/cms/images/7JyyaOyDBp5KY8pk?width=800&height=800&quality=95&format=auto",
      "pumpFunUrl": "https://pump.fun/coin/2xan3NB3HWAD1QzGwKjjP629BxpCykB9nH1kGGF1pump",
      "fallbackUrl": "https://dexscreener.com/solana/2xan3nb3hwad1qzgwkjjp629bxpcykb9nh1kggf1pump",
      "label": "Boosted Pump.fun coin",
      "sourceName": "Public meme radar",
      "priceUsd": 0.000003752,
      "priceChange24h": 56.29,
      "marketCapUsd": 3752.45,
      "volume24hUsd": 88916.67,
      "lastUpdated": "2026-05-25T08:15:02.499Z",
      "sources": [
        "dexscreener"
      ],
      "confidence": 1
    },
    {
      "rank": 17,
      "name": "America Is Back",
      "symbol": "AMERICA",
      "mint": "AVA8YuCsD2YgUSpdv3Hb2cjpdf8XAhGwyXmchxwopump",
      "imageUrl": "https://cdn.dexscreener.com/cms/images/2zaZnFzRL-fCSXIH?width=800&height=800&quality=95&format=auto",
      "pumpFunUrl": "https://pump.fun/coin/AVA8YuCsD2YgUSpdv3Hb2cjpdf8XAhGwyXmchxwopump",
      "fallbackUrl": "https://dexscreener.com/solana/ava8yucsd2yguspdv3hb2cjpdf8xahgwyxmchxwopump",
      "label": "Boosted Pump.fun coin",
      "sourceName": "Public meme radar",
      "priceUsd": 0.001196,
      "priceChange24h": 38.7,
      "marketCapUsd": 1196043,
      "volume24hUsd": 393144.84,
      "lastUpdated": "2026-05-25T08:15:02.499Z",
      "sources": [
        "dexscreener"
      ],
      "confidence": 1
    },
    {
      "rank": 18,
      "name": "The Tesla Squirrel",
      "symbol": "TNUT",
      "mint": "4ZzBD4eQF8CuvrHumVqccfD35QpN7jUnsghpwc1tpump",
      "imageUrl": "https://cdn.dexscreener.com/cms/images/pTDjTCb9XHEEWiY2?width=800&height=800&quality=95&format=auto",
      "pumpFunUrl": "https://pump.fun/coin/4ZzBD4eQF8CuvrHumVqccfD35QpN7jUnsghpwc1tpump",
      "fallbackUrl": "https://dexscreener.com/solana/4zzbd4eqf8cuvrhumvqccfd35qpn7junsghpwc1tpump",
      "label": "High-cap Pump.fun coin",
      "sourceName": "Public meme radar",
      "priceUsd": 0.00004731,
      "priceChange24h": 34.1,
      "marketCapUsd": 47310,
      "volume24hUsd": 191848.21,
      "lastUpdated": "2026-05-25T08:15:02.500Z",
      "sources": [
        "dexscreener"
      ],
      "confidence": 1
    },
    {
      "rank": 19,
      "name": "TOES",
      "symbol": "TOESCOIN",
      "mint": "6ehEcTMCc85aNF4x9CWx8HuvWGhxQtvKdhKVf2HDpump",
      "imageUrl": "https://cdn.dexscreener.com/cms/images/eEd07gpIegaJRCp3?width=800&height=800&quality=95&format=auto",
      "pumpFunUrl": "https://pump.fun/coin/6ehEcTMCc85aNF4x9CWx8HuvWGhxQtvKdhKVf2HDpump",
      "fallbackUrl": "https://dexscreener.com/solana/6ehectmcc85anf4x9cwx8huvwghxqtvkdhkvf2hdpump",
      "label": "Boosted Pump.fun coin",
      "sourceName": "Public meme radar",
      "priceUsd": 0.01584,
      "priceChange24h": 29.56,
      "marketCapUsd": 15841221,
      "volume24hUsd": 1298023.08,
      "lastUpdated": "2026-05-25T08:15:02.499Z",
      "sources": [
        "dexscreener"
      ],
      "confidence": 1
    },
    {
      "rank": 20,
      "name": "TOESCOIN",
      "symbol": "TOES",
      "mint": "toescoin",
      "imageUrl": "https://coin-images.coingecko.com/coins/images/102173370/large/111111.png?1779223810",
      "pumpFunUrl": "",
      "fallbackUrl": "https://www.coingecko.com/en/coins/toescoin",
      "label": "CoinGecko Solana meme",
      "sourceName": "CoinGecko",
      "priceUsd": 0.01589151,
      "priceChange24h": 28.69668,
      "marketCapUsd": 16490591,
      "volume24hUsd": 1298215,
      "lastUpdated": "2026-05-25T08:15:02.865Z",
      "sources": [
        "coingecko"
      ],
      "confidence": 1
    },
    {
      "rank": 21,
      "name": "Purple Troll",
      "symbol": "PTROLL",
      "mint": "HbugFhaL4ijduGiHcY4uT6CNgX58Qac9djsAFo7Dpump",
      "imageUrl": "https://cdn.dexscreener.com/cms/images/hhxtGWKnA9v0dGG9?width=800&height=800&quality=95&format=auto",
      "pumpFunUrl": "https://pump.fun/coin/HbugFhaL4ijduGiHcY4uT6CNgX58Qac9djsAFo7Dpump",
      "fallbackUrl": "https://dexscreener.com/solana/hbugfhal4ijdugihcy4ut6cngx58qac9djsafo7dpump",
      "label": "Boosted Pump.fun coin",
      "sourceName": "Public meme radar",
      "priceUsd": 0.0001088,
      "priceChange24h": 28.58,
      "marketCapUsd": 107711,
      "volume24hUsd": 63118.86,
      "lastUpdated": "2026-05-25T08:15:02.499Z",
      "sources": [
        "dexscreener"
      ],
      "confidence": 1
    },
    {
      "rank": 22,
      "name": "Believe",
      "symbol": "BELIEVE",
      "mint": "ben-pasternak",
      "imageUrl": "https://coin-images.coingecko.com/coins/images/53916/large/launchcoin.jpg?1747131421",
      "pumpFunUrl": "",
      "fallbackUrl": "https://www.coingecko.com/en/coins/ben-pasternak",
      "label": "CoinGecko Solana meme",
      "sourceName": "CoinGecko",
      "priceUsd": 0.00239518,
      "priceChange24h": 24.64269,
      "marketCapUsd": 3073523,
      "volume24hUsd": 3424991,
      "lastUpdated": "2026-05-25T08:15:02.865Z",
      "sources": [
        "coingecko"
      ],
      "confidence": 1
    },
    {
      "rank": 23,
      "name": "Virl.fun",
      "symbol": "VIRL",
      "mint": "BiywH8Eq2CbGhwMHKwCnfTiccWJwN7r1Q4Qn9hsypump",
      "imageUrl": "https://coin-images.coingecko.com/coins/images/102173296/large/unfyyhsotkhcrdjw6k19fxx0ohhp.?1778854488",
      "pumpFunUrl": "https://pump.fun/coin/BiywH8Eq2CbGhwMHKwCnfTiccWJwN7r1Q4Qn9hsypump",
      "fallbackUrl": "https://www.geckoterminal.com/solana/pools/8PX97NP5WY871SmsZwHqYL9z97k3vzHGjvKFvAT7cARz",
      "label": "GeckoTerminal trending pool",
      "sourceName": "GeckoTerminal",
      "priceUsd": 0.0033047788104624055,
      "priceChange24h": 18.832,
      "marketCapUsd": 3300750.30074857,
      "volume24hUsd": 1099748.52859285,
      "liquidityUsd": 188839.8554,
      "coingeckoId": "virl-fun",
      "lastUpdated": "2026-05-25T08:15:03.080Z",
      "sources": [
        "gecko-terminal"
      ],
      "confidence": 1
    },
    {
      "rank": 24,
      "name": "World Cup Coin",
      "symbol": "WORLDCUP",
      "mint": "33eum82LaAhtv5YkUq1BdwEviSErH5CnFxqVNLT5pump",
      "imageUrl": "https://assets.geckoterminal.com/u5szff4v098vne7swtcjmkmhjvra",
      "pumpFunUrl": "https://pump.fun/coin/33eum82LaAhtv5YkUq1BdwEviSErH5CnFxqVNLT5pump",
      "fallbackUrl": "https://www.geckoterminal.com/solana/pools/ETMhxtENfkMK85TAcveEbZdBv9htziWzDSddmShRP2wB",
      "label": "GeckoTerminal trending pool",
      "sourceName": "GeckoTerminal",
      "priceUsd": 0.00712115377897092,
      "priceChange24h": 18.492,
      "marketCapUsd": 7070442.701,
      "volume24hUsd": 792727.282574491,
      "liquidityUsd": 289925.6746,
      "lastUpdated": "2026-05-25T08:15:03.080Z",
      "sources": [
        "gecko-terminal"
      ],
      "confidence": 1
    },
    {
      "rank": 25,
      "name": "Virl.fun",
      "symbol": "VIRL",
      "mint": "virl-fun",
      "imageUrl": "https://coin-images.coingecko.com/coins/images/102173296/large/unfyyhsotkhcrdjw6k19fxx0ohhp.?1778854488",
      "pumpFunUrl": "",
      "fallbackUrl": "https://www.coingecko.com/en/coins/virl-fun",
      "label": "CoinGecko Solana meme",
      "sourceName": "CoinGecko",
      "priceUsd": 0.00334163,
      "priceChange24h": 17.97064,
      "marketCapUsd": 3419374,
      "volume24hUsd": 3915464,
      "lastUpdated": "2026-05-25T08:15:02.865Z",
      "sources": [
        "coingecko"
      ],
      "confidence": 1
    },
    {
      "rank": 26,
      "name": "Collector Crypt",
      "symbol": "CARDS",
      "mint": "CARDSccUMFKoPRZxt5vt3ksUbxEFEcnZ3H2pd3dKxYjp",
      "imageUrl": "https://coin-images.coingecko.com/coins/images/68728/large/cards-logo.jpeg?1756534539",
      "pumpFunUrl": "",
      "fallbackUrl": "https://www.geckoterminal.com/solana/pools/HnhpJPJgBG2KwniMTNW8cVBHvk1hFog3RC3kjnyc23tD",
      "label": "GeckoTerminal trending pool",
      "sourceName": "GeckoTerminal",
      "priceUsd": 0.15564969894294525,
      "priceChange24h": 13.025,
      "marketCapUsd": 40402276.3649381,
      "volume24hUsd": 2034064.40195512,
      "liquidityUsd": 2432210.5257,
      "coingeckoId": "collector-crypt",
      "lastUpdated": "2026-05-25T08:15:03.080Z",
      "sources": [
        "gecko-terminal",
        "raydium"
      ],
      "confidence": 2
    },
    {
      "rank": 27,
      "name": "Zerebro",
      "symbol": "ZEREBRO",
      "mint": "zerebro",
      "imageUrl": "https://coin-images.coingecko.com/coins/images/51289/large/zerebro_2.png?1730588883",
      "pumpFunUrl": "",
      "fallbackUrl": "https://www.coingecko.com/en/coins/zerebro",
      "label": "CoinGecko Solana meme",
      "sourceName": "CoinGecko",
      "priceUsd": 0.02300117,
      "priceChange24h": 9.48116,
      "marketCapUsd": 22727169,
      "volume24hUsd": 3640019,
      "lastUpdated": "2026-05-25T08:15:02.865Z",
      "sources": [
        "coingecko"
      ],
      "confidence": 1
    },
    {
      "rank": 28,
      "name": "Bull",
      "symbol": "BULL",
      "mint": "bull-5",
      "imageUrl": "https://coin-images.coingecko.com/coins/images/102172695/large/BULL.jpg?1776225921",
      "pumpFunUrl": "",
      "fallbackUrl": "https://www.coingecko.com/en/coins/bull-5",
      "label": "CoinGecko Solana meme",
      "sourceName": "CoinGecko",
      "priceUsd": 0.00555905,
      "priceChange24h": 9.45678,
      "marketCapUsd": 5547466,
      "volume24hUsd": 1934042,
      "lastUpdated": "2026-05-25T08:15:02.865Z",
      "sources": [
        "coingecko"
      ],
      "confidence": 1
    },
    {
      "rank": 29,
      "name": "Bull",
      "symbol": "BULL",
      "mint": "3TYgKwkE2Y3rxdw9osLRSpxpXmSC1C1oo19W9KHspump",
      "imageUrl": "https://cdn.dexscreener.com/cms/images/mV3BYbgW_ebV6G6c?width=800&height=800&quality=95&format=auto",
      "pumpFunUrl": "https://pump.fun/coin/3TYgKwkE2Y3rxdw9osLRSpxpXmSC1C1oo19W9KHspump",
      "fallbackUrl": "https://dexscreener.com/solana/3tygkwke2y3rxdw9oslrspxpxmsc1c1oo19w9khspump",
      "label": "Boosted Pump.fun coin",
      "sourceName": "Public meme radar",
      "priceUsd": 0.005525,
      "priceChange24h": 8.64,
      "marketCapUsd": 5525426,
      "volume24hUsd": 739098.74,
      "lastUpdated": "2026-05-25T08:15:02.499Z",
      "sources": [
        "dexscreener"
      ],
      "confidence": 1
    },
    {
      "rank": 30,
      "name": "aura",
      "symbol": "AURA",
      "mint": "aura-on-sol",
      "imageUrl": "https://coin-images.coingecko.com/coins/images/38376/large/aura_logo_200x200-01-01.png?1751114135",
      "pumpFunUrl": "",
      "fallbackUrl": "https://www.coingecko.com/en/coins/aura-on-sol",
      "label": "CoinGecko Solana meme",
      "sourceName": "CoinGecko",
      "priceUsd": 0.01713607,
      "priceChange24h": 5.90308,
      "marketCapUsd": 16299930,
      "volume24hUsd": 1610643,
      "lastUpdated": "2026-05-25T08:15:02.865Z",
      "sources": [
        "coingecko"
      ],
      "confidence": 1
    }
  ],
  "highCap": [
    {
      "rank": 1,
      "name": "Pudgy Penguins",
      "symbol": "PENGU",
      "mint": "pudgy-penguins",
      "imageUrl": "https://coin-images.coingecko.com/coins/images/52622/large/PUDGY_PENGUINS_PENGU_PFP.png?1733809110",
      "pumpFunUrl": "",
      "fallbackUrl": "https://www.coingecko.com/en/coins/pudgy-penguins",
      "label": "High-cap",
      "sourceName": "CoinGecko",
      "priceUsd": 0.00901053,
      "priceChange24h": -1.19549,
      "marketCapUsd": 566597823,
      "volume24hUsd": 82742099,
      "lastUpdated": "2026-05-25T08:15:02.865Z",
      "sources": [
        "coingecko"
      ],
      "confidence": 1
    },
    {
      "rank": 2,
      "name": "Bonk",
      "symbol": "BONK",
      "mint": "bonk",
      "imageUrl": "https://coin-images.coingecko.com/coins/images/28600/large/bonk.jpg?1696527587",
      "pumpFunUrl": "",
      "fallbackUrl": "https://www.coingecko.com/en/coins/bonk",
      "label": "High-cap",
      "sourceName": "CoinGecko",
      "priceUsd": 0.00000609,
      "priceChange24h": 0.59462,
      "marketCapUsd": 537240928,
      "volume24hUsd": 24086254,
      "lastUpdated": "2026-05-25T08:15:02.865Z",
      "sources": [
        "coingecko"
      ],
      "confidence": 1
    },
    {
      "rank": 3,
      "name": "Official Trump",
      "symbol": "TRUMP",
      "mint": "official-trump",
      "imageUrl": "https://coin-images.coingecko.com/coins/images/53746/large/trump.png?1737171561",
      "pumpFunUrl": "",
      "fallbackUrl": "https://www.coingecko.com/en/coins/official-trump",
      "label": "High-cap",
      "sourceName": "CoinGecko",
      "priceUsd": 2.1,
      "priceChange24h": -0.37897,
      "marketCapUsd": 498409436,
      "volume24hUsd": 44087267,
      "lastUpdated": "2026-05-25T08:15:02.865Z",
      "sources": [
        "coingecko"
      ],
      "confidence": 1
    },
    {
      "rank": 4,
      "name": "dogwifhat",
      "symbol": "WIF",
      "mint": "dogwifcoin",
      "imageUrl": "https://coin-images.coingecko.com/coins/images/33566/large/dogwifhat.jpg?1702499428",
      "pumpFunUrl": "",
      "fallbackUrl": "https://www.coingecko.com/en/coins/dogwifcoin",
      "label": "High-cap",
      "sourceName": "CoinGecko",
      "priceUsd": 0.189488,
      "priceChange24h": -1.09738,
      "marketCapUsd": 189802467,
      "volume24hUsd": 24683015,
      "lastUpdated": "2026-05-25T08:15:02.865Z",
      "sources": [
        "coingecko"
      ],
      "confidence": 1
    },
    {
      "rank": 5,
      "name": "Fartcoin",
      "symbol": "FARTCOIN",
      "mint": "fartcoin",
      "imageUrl": "https://coin-images.coingecko.com/coins/images/50891/large/fart.jpg?1729503972",
      "pumpFunUrl": "",
      "fallbackUrl": "https://www.coingecko.com/en/coins/fartcoin",
      "label": "High-cap",
      "sourceName": "CoinGecko",
      "priceUsd": 0.181297,
      "priceChange24h": -0.79926,
      "marketCapUsd": 181301436,
      "volume24hUsd": 18991909,
      "lastUpdated": "2026-05-25T08:15:02.865Z",
      "sources": [
        "coingecko"
      ],
      "confidence": 1
    },
    {
      "rank": 6,
      "name": "TROLL",
      "symbol": "TROLL",
      "mint": "5UUH9RTDiSpq6HKS6bp4NdU9PNJpXRXuiw6ShBTBhgH2",
      "imageUrl": "https://coin-images.coingecko.com/coins/images/55282/large/Untitled_design.png?1777015928",
      "pumpFunUrl": "",
      "fallbackUrl": "https://www.geckoterminal.com/solana/pools/4w2cysotX6czaUGmmWg13hDpY4QEMG2CzeKYEQyK9Ama",
      "label": "High-cap",
      "sourceName": "GeckoTerminal",
      "priceUsd": 0.10591457313188919,
      "priceChange24h": -11.499,
      "marketCapUsd": 105784597.708264,
      "volume24hUsd": 1444187.80931983,
      "liquidityUsd": 3918113.6263,
      "coingeckoId": "troll-2",
      "lastUpdated": "2026-05-25T08:15:03.080Z",
      "sources": [
        "gecko-terminal"
      ],
      "confidence": 1
    },
    {
      "rank": 7,
      "name": "TROLL",
      "symbol": "TROLL",
      "mint": "troll-2",
      "imageUrl": "https://coin-images.coingecko.com/coins/images/55282/large/Untitled_design.png?1777015928",
      "pumpFunUrl": "",
      "fallbackUrl": "https://www.coingecko.com/en/coins/troll-2",
      "label": "High-cap",
      "sourceName": "CoinGecko",
      "priceUsd": 0.105547,
      "priceChange24h": -11.70556,
      "marketCapUsd": 105033075,
      "volume24hUsd": 7089767,
      "lastUpdated": "2026-05-25T08:15:02.865Z",
      "sources": [
        "coingecko"
      ],
      "confidence": 1
    },
    {
      "rank": 8,
      "name": "Melania Meme",
      "symbol": "MELANIA",
      "mint": "melania-meme",
      "imageUrl": "https://coin-images.coingecko.com/coins/images/53775/large/melania-meme.png?1737329885",
      "pumpFunUrl": "",
      "fallbackUrl": "https://www.coingecko.com/en/coins/melania-meme",
      "label": "High-cap",
      "sourceName": "CoinGecko",
      "priceUsd": 0.095485,
      "priceChange24h": -1.17779,
      "marketCapUsd": 91043353,
      "volume24hUsd": 6070879,
      "lastUpdated": "2026-05-25T08:15:02.865Z",
      "sources": [
        "coingecko"
      ],
      "confidence": 1
    },
    {
      "rank": 9,
      "name": "Comedian",
      "symbol": "BAN",
      "mint": "comedian",
      "imageUrl": "https://coin-images.coingecko.com/coins/images/51100/large/ban.jpg?1730085215",
      "pumpFunUrl": "",
      "fallbackUrl": "https://www.coingecko.com/en/coins/comedian",
      "label": "High-cap",
      "sourceName": "CoinGecko",
      "priceUsd": 0.088318,
      "priceChange24h": -8.29081,
      "marketCapUsd": 88371605,
      "volume24hUsd": 6288283,
      "lastUpdated": "2026-05-25T08:15:02.865Z",
      "sources": [
        "coingecko"
      ],
      "confidence": 1
    },
    {
      "rank": 10,
      "name": "Useless Coin",
      "symbol": "USELESS",
      "mint": "useless-3",
      "imageUrl": "https://coin-images.coingecko.com/coins/images/55684/large/coingeckoupdate.png?1755203747",
      "pumpFunUrl": "",
      "fallbackUrl": "https://www.coingecko.com/en/coins/useless-3",
      "label": "High-cap",
      "sourceName": "CoinGecko",
      "priceUsd": 0.078833,
      "priceChange24h": 5.406,
      "marketCapUsd": 79300271,
      "volume24hUsd": 8451907,
      "lastUpdated": "2026-05-25T08:15:02.865Z",
      "sources": [
        "coingecko"
      ],
      "confidence": 1
    },
    {
      "rank": 11,
      "name": "Baby Doge Coin",
      "symbol": "BABYDOGE",
      "mint": "baby-doge-coin",
      "imageUrl": "https://coin-images.coingecko.com/coins/images/16125/large/babydoge.jpg?1696515731",
      "pumpFunUrl": "",
      "fallbackUrl": "https://www.coingecko.com/en/coins/baby-doge-coin",
      "label": "High-cap",
      "sourceName": "CoinGecko",
      "priceUsd": 4.00826e-10,
      "priceChange24h": 1.04247,
      "marketCapUsd": 73222337,
      "volume24hUsd": 2375119,
      "lastUpdated": "2026-05-25T08:15:02.865Z",
      "sources": [
        "coingecko"
      ],
      "confidence": 1
    },
    {
      "rank": 12,
      "name": "Peanut the Squirrel",
      "symbol": "PNUT",
      "mint": "peanut-the-squirrel",
      "imageUrl": "https://coin-images.coingecko.com/coins/images/51301/large/Peanut_the_Squirrel.png?1734941241",
      "pumpFunUrl": "",
      "fallbackUrl": "https://www.coingecko.com/en/coins/peanut-the-squirrel",
      "label": "High-cap",
      "sourceName": "CoinGecko",
      "priceUsd": 0.054717,
      "priceChange24h": 1.98321,
      "marketCapUsd": 54751129,
      "volume24hUsd": 10824084,
      "lastUpdated": "2026-05-25T08:15:02.865Z",
      "sources": [
        "coingecko"
      ],
      "confidence": 1
    },
    {
      "rank": 13,
      "name": "Popcat",
      "symbol": "POPCAT",
      "mint": "popcat",
      "imageUrl": "https://coin-images.coingecko.com/coins/images/33760/large/image.jpg?1702964227",
      "pumpFunUrl": "",
      "fallbackUrl": "https://www.coingecko.com/en/coins/popcat",
      "label": "High-cap",
      "sourceName": "CoinGecko",
      "priceUsd": 0.055547,
      "priceChange24h": 2.12154,
      "marketCapUsd": 54457814,
      "volume24hUsd": 11475093,
      "lastUpdated": "2026-05-25T08:15:02.865Z",
      "sources": [
        "coingecko"
      ],
      "confidence": 1
    },
    {
      "rank": 14,
      "name": "Moo Deng",
      "symbol": "MOODENG",
      "mint": "moo-deng",
      "imageUrl": "https://coin-images.coingecko.com/coins/images/50264/large/MOODENG.jpg?1726726975",
      "pumpFunUrl": "",
      "fallbackUrl": "https://www.coingecko.com/en/coins/moo-deng",
      "label": "High-cap",
      "sourceName": "CoinGecko",
      "priceUsd": 0.050801,
      "priceChange24h": -0.67375,
      "marketCapUsd": 50318128,
      "volume24hUsd": 8025523,
      "lastUpdated": "2026-05-25T08:15:02.865Z",
      "sources": [
        "coingecko"
      ],
      "confidence": 1
    },
    {
      "rank": 15,
      "name": "cat in a dogs world",
      "symbol": "MEW",
      "mint": "cat-in-a-dogs-world",
      "imageUrl": "https://coin-images.coingecko.com/coins/images/36440/large/MEW.png?1711442286",
      "pumpFunUrl": "",
      "fallbackUrl": "https://www.coingecko.com/en/coins/cat-in-a-dogs-world",
      "label": "High-cap",
      "sourceName": "CoinGecko",
      "priceUsd": 0.00054249,
      "priceChange24h": -0.17671,
      "marketCapUsd": 48238252,
      "volume24hUsd": 4255219,
      "lastUpdated": "2026-05-25T08:15:02.865Z",
      "sources": [
        "coingecko"
      ],
      "confidence": 1
    },
    {
      "rank": 16,
      "name": "monji",
      "symbol": "MONJI",
      "mint": "monji",
      "imageUrl": "https://coin-images.coingecko.com/coins/images/102173311/large/pAxU_0h5_400x400.jpg?1778948517",
      "pumpFunUrl": "",
      "fallbackUrl": "https://www.coingecko.com/en/coins/monji",
      "label": "High-cap",
      "sourceName": "CoinGecko",
      "priceUsd": 0.03534192,
      "priceChange24h": -32.27369,
      "marketCapUsd": 41973241,
      "volume24hUsd": 1414579,
      "lastUpdated": "2026-05-25T08:15:02.865Z",
      "sources": [
        "coingecko"
      ],
      "confidence": 1
    },
    {
      "rank": 17,
      "name": "Collector Crypt",
      "symbol": "CARDS",
      "mint": "CARDSccUMFKoPRZxt5vt3ksUbxEFEcnZ3H2pd3dKxYjp",
      "imageUrl": "https://coin-images.coingecko.com/coins/images/68728/large/cards-logo.jpeg?1756534539",
      "pumpFunUrl": "",
      "fallbackUrl": "https://www.geckoterminal.com/solana/pools/HnhpJPJgBG2KwniMTNW8cVBHvk1hFog3RC3kjnyc23tD",
      "label": "High-cap",
      "sourceName": "GeckoTerminal",
      "priceUsd": 0.15564969894294525,
      "priceChange24h": 13.025,
      "marketCapUsd": 40402276.3649381,
      "volume24hUsd": 2034064.40195512,
      "liquidityUsd": 2432210.5257,
      "coingeckoId": "collector-crypt",
      "lastUpdated": "2026-05-25T08:15:03.080Z",
      "sources": [
        "gecko-terminal",
        "raydium"
      ],
      "confidence": 2
    },
    {
      "rank": 18,
      "name": "Not in Employment, Education, or Training",
      "symbol": "NEET",
      "mint": "neet",
      "imageUrl": "https://coin-images.coingecko.com/coins/images/55411/large/neet.jpg?1745850587",
      "pumpFunUrl": "",
      "fallbackUrl": "https://www.coingecko.com/en/coins/neet",
      "label": "High-cap",
      "sourceName": "CoinGecko",
      "priceUsd": 0.03988011,
      "priceChange24h": -2.34277,
      "marketCapUsd": 39981167,
      "volume24hUsd": 2183703,
      "lastUpdated": "2026-05-25T08:15:02.865Z",
      "sources": [
        "coingecko"
      ],
      "confidence": 1
    },
    {
      "rank": 19,
      "name": "Gigachad",
      "symbol": "GIGA",
      "mint": "gigachad-2",
      "imageUrl": "https://coin-images.coingecko.com/coins/images/34755/large/IMG_0015.png?1705957165",
      "pumpFunUrl": "",
      "fallbackUrl": "https://www.coingecko.com/en/coins/gigachad-2",
      "label": "High-cap",
      "sourceName": "CoinGecko",
      "priceUsd": 0.00394909,
      "priceChange24h": -3.83155,
      "marketCapUsd": 38103090,
      "volume24hUsd": 1753713,
      "lastUpdated": "2026-05-25T08:15:02.865Z",
      "sources": [
        "coingecko"
      ],
      "confidence": 1
    },
    {
      "rank": 20,
      "name": "BOOK OF MEME",
      "symbol": "BOME",
      "mint": "book-of-meme",
      "imageUrl": "https://coin-images.coingecko.com/coins/images/36071/large/bome.png?1710407255",
      "pumpFunUrl": "",
      "fallbackUrl": "https://www.coingecko.com/en/coins/book-of-meme",
      "label": "High-cap",
      "sourceName": "CoinGecko",
      "priceUsd": 0.00054085,
      "priceChange24h": 1.63199,
      "marketCapUsd": 37560024,
      "volume24hUsd": 11793638,
      "lastUpdated": "2026-05-25T08:15:02.865Z",
      "sources": [
        "coingecko"
      ],
      "confidence": 1
    },
    {
      "rank": 21,
      "name": "Moonbirds",
      "symbol": "BIRB",
      "mint": "moonbirds",
      "imageUrl": "https://coin-images.coingecko.com/coins/images/69732/large/birb-logo.jpg?1759413928",
      "pumpFunUrl": "",
      "fallbackUrl": "https://www.coingecko.com/en/coins/moonbirds",
      "label": "High-cap",
      "sourceName": "CoinGecko",
      "priceUsd": 0.128346,
      "priceChange24h": -2.07863,
      "marketCapUsd": 36669746,
      "volume24hUsd": 3354877,
      "lastUpdated": "2026-05-25T08:15:02.865Z",
      "sources": [
        "coingecko"
      ],
      "confidence": 1
    },
    {
      "rank": 22,
      "name": "Zerebro",
      "symbol": "ZEREBRO",
      "mint": "zerebro",
      "imageUrl": "https://coin-images.coingecko.com/coins/images/51289/large/zerebro_2.png?1730588883",
      "pumpFunUrl": "",
      "fallbackUrl": "https://www.coingecko.com/en/coins/zerebro",
      "label": "High-cap",
      "sourceName": "CoinGecko",
      "priceUsd": 0.02300117,
      "priceChange24h": 9.48116,
      "marketCapUsd": 22727169,
      "volume24hUsd": 3640019,
      "lastUpdated": "2026-05-25T08:15:02.865Z",
      "sources": [
        "coingecko"
      ],
      "confidence": 1
    },
    {
      "rank": 23,
      "name": "pippin",
      "symbol": "PIPPIN",
      "mint": "pippin",
      "imageUrl": "https://coin-images.coingecko.com/coins/images/51589/large/pippin_logo.png?1731570163",
      "pumpFunUrl": "",
      "fallbackUrl": "https://www.coingecko.com/en/coins/pippin",
      "label": "High-cap",
      "sourceName": "CoinGecko",
      "priceUsd": 0.02242078,
      "priceChange24h": -1.52206,
      "marketCapUsd": 22396003,
      "volume24hUsd": 4345402,
      "lastUpdated": "2026-05-25T08:15:02.865Z",
      "sources": [
        "coingecko"
      ],
      "confidence": 1
    },
    {
      "rank": 24,
      "name": "Manifesting",
      "symbol": "MANIFEST",
      "mint": "manifesting",
      "imageUrl": "https://coin-images.coingecko.com/coins/images/102173340/large/manifesting.jpg?1779374701",
      "pumpFunUrl": "",
      "fallbackUrl": "https://www.coingecko.com/en/coins/manifesting",
      "label": "High-cap",
      "sourceName": "CoinGecko",
      "priceUsd": 0.02502568,
      "priceChange24h": -6.29777,
      "marketCapUsd": 22264118,
      "volume24hUsd": 1283187,
      "lastUpdated": "2026-05-25T08:15:02.865Z",
      "sources": [
        "coingecko"
      ],
      "confidence": 1
    },
    {
      "rank": 25,
      "name": "PONKE",
      "symbol": "PONKE",
      "mint": "ponke",
      "imageUrl": "https://coin-images.coingecko.com/coins/images/33929/large/ponke-logo.png?1747200908",
      "pumpFunUrl": "",
      "fallbackUrl": "https://www.coingecko.com/en/coins/ponke",
      "label": "High-cap",
      "sourceName": "CoinGecko",
      "priceUsd": 0.03935528,
      "priceChange24h": -0.43859,
      "marketCapUsd": 21847930,
      "volume24hUsd": 1846869,
      "lastUpdated": "2026-05-25T08:15:02.865Z",
      "sources": [
        "coingecko"
      ],
      "confidence": 1
    },
    {
      "rank": 26,
      "name": "Vine",
      "symbol": "VINE",
      "mint": "vine",
      "imageUrl": "https://coin-images.coingecko.com/coins/images/53859/large/vine.jpg?1737613523",
      "pumpFunUrl": "",
      "fallbackUrl": "https://www.coingecko.com/en/coins/vine",
      "label": "High-cap",
      "sourceName": "CoinGecko",
      "priceUsd": 0.01780056,
      "priceChange24h": 3.54445,
      "marketCapUsd": 17803044,
      "volume24hUsd": 4144338,
      "lastUpdated": "2026-05-25T08:15:02.865Z",
      "sources": [
        "coingecko"
      ],
      "confidence": 1
    },
    {
      "rank": 27,
      "name": "Goatseus Maximus",
      "symbol": "GOAT",
      "mint": "goatseus-maximus",
      "imageUrl": "https://coin-images.coingecko.com/coins/images/50717/large/GOAT_LOGO_NEW.jpg?1731292759",
      "pumpFunUrl": "",
      "fallbackUrl": "https://www.coingecko.com/en/coins/goatseus-maximus",
      "label": "High-cap",
      "sourceName": "CoinGecko",
      "priceUsd": 0.01721739,
      "priceChange24h": 0.14892,
      "marketCapUsd": 17244860,
      "volume24hUsd": 2562298,
      "lastUpdated": "2026-05-25T08:15:02.865Z",
      "sources": [
        "coingecko"
      ],
      "confidence": 1
    },
    {
      "rank": 28,
      "name": "TOESCOIN",
      "symbol": "TOES",
      "mint": "toescoin",
      "imageUrl": "https://coin-images.coingecko.com/coins/images/102173370/large/111111.png?1779223810",
      "pumpFunUrl": "",
      "fallbackUrl": "https://www.coingecko.com/en/coins/toescoin",
      "label": "High-cap",
      "sourceName": "CoinGecko",
      "priceUsd": 0.01589151,
      "priceChange24h": 28.69668,
      "marketCapUsd": 16490591,
      "volume24hUsd": 1298215,
      "lastUpdated": "2026-05-25T08:15:02.865Z",
      "sources": [
        "coingecko"
      ],
      "confidence": 1
    },
    {
      "rank": 29,
      "name": "aura",
      "symbol": "AURA",
      "mint": "aura-on-sol",
      "imageUrl": "https://coin-images.coingecko.com/coins/images/38376/large/aura_logo_200x200-01-01.png?1751114135",
      "pumpFunUrl": "",
      "fallbackUrl": "https://www.coingecko.com/en/coins/aura-on-sol",
      "label": "High-cap",
      "sourceName": "CoinGecko",
      "priceUsd": 0.01713607,
      "priceChange24h": 5.90308,
      "marketCapUsd": 16299930,
      "volume24hUsd": 1610643,
      "lastUpdated": "2026-05-25T08:15:02.865Z",
      "sources": [
        "coingecko"
      ],
      "confidence": 1
    },
    {
      "rank": 30,
      "name": "TOES",
      "symbol": "TOESCOIN",
      "mint": "6ehEcTMCc85aNF4x9CWx8HuvWGhxQtvKdhKVf2HDpump",
      "imageUrl": "https://cdn.dexscreener.com/cms/images/eEd07gpIegaJRCp3?width=800&height=800&quality=95&format=auto",
      "pumpFunUrl": "https://pump.fun/coin/6ehEcTMCc85aNF4x9CWx8HuvWGhxQtvKdhKVf2HDpump",
      "fallbackUrl": "https://dexscreener.com/solana/6ehectmcc85anf4x9cwx8huvwghxqtvkdhkvf2hdpump",
      "label": "High-cap",
      "sourceName": "Public meme radar",
      "priceUsd": 0.01584,
      "priceChange24h": 29.56,
      "marketCapUsd": 15841221,
      "volume24hUsd": 1298023.08,
      "lastUpdated": "2026-05-25T08:15:02.499Z",
      "sources": [
        "dexscreener"
      ],
      "confidence": 1
    }
  ],
  "lowCap": [
    {
      "rank": 1,
      "name": "cannot be rich without wealth",
      "symbol": "WEALTH",
      "mint": "8C2wF9dbok8Zt3hWux6VL37ZJducsdi7TK7R6rRNpump",
      "imageUrl": "https://cdn.dexscreener.com/cms/images/0j_vxHLRD5YQ4doS?width=800&height=800&quality=95&format=auto",
      "pumpFunUrl": "https://pump.fun/coin/8C2wF9dbok8Zt3hWux6VL37ZJducsdi7TK7R6rRNpump",
      "fallbackUrl": "https://dexscreener.com/solana/8c2wf9dbok8zt3hwux6vl37zjducsdi7tk7r6rrnpump",
      "label": "Low-cap discovery",
      "sourceName": "Public meme radar",
      "priceUsd": 0.000002796,
      "priceChange24h": -98,
      "marketCapUsd": 2797,
      "volume24hUsd": 2585372.88,
      "lastUpdated": "2026-05-25T08:15:02.499Z",
      "sources": [
        "dexscreener"
      ],
      "confidence": 1
    },
    {
      "rank": 2,
      "name": "endless twap bid",
      "symbol": "ETB",
      "mint": "Cjo46uRW2yeF2uXLn2phrVZZyZ1sfnrMNutfrhZopump",
      "imageUrl": "https://assets.geckoterminal.com/kmlkw4xhuglgurld6zvmn9hql2bc",
      "pumpFunUrl": "https://pump.fun/coin/Cjo46uRW2yeF2uXLn2phrVZZyZ1sfnrMNutfrhZopump",
      "fallbackUrl": "https://www.geckoterminal.com/solana/pools/FMT7qeayftbQteCWbNmZWmHpEojjVzLBLtfkFUHWRP8h",
      "label": "Low-cap discovery",
      "sourceName": "GeckoTerminal",
      "priceUsd": 0.00011147118564953024,
      "priceChange24h": 293.69,
      "marketCapUsd": 111471.1856,
      "volume24hUsd": 2148658.71118325,
      "liquidityUsd": 29089.0712,
      "lastUpdated": "2026-05-25T08:15:03.080Z",
      "sources": [
        "gecko-terminal"
      ],
      "confidence": 1
    },
    {
      "rank": 3,
      "name": "Paraloom",
      "symbol": "PARALOOM",
      "mint": "Br1JxELQYP34YdRW4gbEPLasHEtyz8eCmT2FvmnYpump",
      "imageUrl": "https://assets.geckoterminal.com/vjdjymhy6yyx0j44xhkjxsojozhu",
      "pumpFunUrl": "https://pump.fun/coin/Br1JxELQYP34YdRW4gbEPLasHEtyz8eCmT2FvmnYpump",
      "fallbackUrl": "https://www.geckoterminal.com/solana/pools/9ekUjhCnJDzqW5QXk41jeKjteUdHquK5DJh8mRDHtqA7",
      "label": "Low-cap discovery",
      "sourceName": "GeckoTerminal",
      "priceUsd": 0.0004593178780395924,
      "priceChange24h": 691.713,
      "marketCapUsd": 466001.9803,
      "volume24hUsd": 1816988.55433654,
      "liquidityUsd": 72549.799,
      "lastUpdated": "2026-05-25T08:15:03.080Z",
      "sources": [
        "gecko-terminal"
      ],
      "confidence": 1
    },
    {
      "rank": 4,
      "name": "BELIEF",
      "symbol": "BELIEF",
      "mint": "5N8zivsMVY13XRnUrqkvS46qf48S6iw4rHB7wjhcpump",
      "imageUrl": "https://assets.geckoterminal.com/zfd8hzds7dw6ojnf138ahqcx620k",
      "pumpFunUrl": "https://pump.fun/coin/5N8zivsMVY13XRnUrqkvS46qf48S6iw4rHB7wjhcpump",
      "fallbackUrl": "https://www.geckoterminal.com/solana/pools/4L29chFWwQ2HC6ZBB7Zr5otKaCQ85rme9tsQ9tioAimm",
      "label": "Low-cap discovery",
      "sourceName": "GeckoTerminal",
      "priceUsd": 0.00006955592895973572,
      "priceChange24h": 91.814,
      "marketCapUsd": 68633.98765,
      "volume24hUsd": 1468607.53222998,
      "liquidityUsd": 22460.6082,
      "lastUpdated": "2026-05-25T08:15:03.080Z",
      "sources": [
        "gecko-terminal"
      ],
      "confidence": 1
    },
    {
      "rank": 5,
      "name": "America is Rich",
      "symbol": "RICHAMERICA",
      "mint": "CLvqTFi16ptkhFLJjZdHyVjouef8aPaqugjYGhURpump",
      "imageUrl": "https://cdn.dexscreener.com/cms/images/LlswItNeE0EFePuV?width=800&height=800&quality=95&format=auto",
      "pumpFunUrl": "https://pump.fun/coin/CLvqTFi16ptkhFLJjZdHyVjouef8aPaqugjYGhURpump",
      "fallbackUrl": "https://dexscreener.com/solana/clvqtfi16ptkhfljjzdhyvjouef8apaqugjyghurpump",
      "label": "Low-cap discovery",
      "sourceName": "Public meme radar",
      "priceUsd": 0.0001903,
      "priceChange24h": 83.47,
      "marketCapUsd": 190350,
      "volume24hUsd": 983502.7,
      "lastUpdated": "2026-05-25T08:15:02.499Z",
      "sources": [
        "dexscreener"
      ],
      "confidence": 1
    },
    {
      "rank": 6,
      "name": "Poor But Proud",
      "symbol": "POOR",
      "mint": "T1YZcgtG7Co3ZzFyZn5K9CjDeHAdEEMVRVt6FP5pump",
      "imageUrl": "https://assets.geckoterminal.com/xki1w47zrzke2b579haksay84hgg",
      "pumpFunUrl": "https://pump.fun/coin/T1YZcgtG7Co3ZzFyZn5K9CjDeHAdEEMVRVt6FP5pump",
      "fallbackUrl": "https://www.geckoterminal.com/solana/pools/9qT5RG4SoAaZTHxjPu9Yh6Pde3cbLuyqY5CqYBZgN8N7",
      "label": "Low-cap discovery",
      "sourceName": "GeckoTerminal",
      "priceUsd": 0.00008505288299339021,
      "priceChange24h": -84.911,
      "marketCapUsd": 85052.88299,
      "volume24hUsd": 965703.750690276,
      "liquidityUsd": 26125.3514,
      "lastUpdated": "2026-05-25T08:15:03.080Z",
      "sources": [
        "gecko-terminal"
      ],
      "confidence": 1
    },
    {
      "rank": 7,
      "name": "GyattCoin",
      "symbol": "GYATT",
      "mint": "GWjQzhiTgHNA7E4nEoYzYPTbwQBJ35h89zjYyyTepump",
      "imageUrl": "https://assets.geckoterminal.com/w0nfb1w60g6nh1d9wawmj5hygpqo",
      "pumpFunUrl": "https://pump.fun/coin/GWjQzhiTgHNA7E4nEoYzYPTbwQBJ35h89zjYyyTepump",
      "fallbackUrl": "https://www.geckoterminal.com/solana/pools/gWGs323SXK8TQEekWKc9dkSEkaSm8eDtEpCR9QSMXeP",
      "label": "Low-cap discovery",
      "sourceName": "GeckoTerminal",
      "priceUsd": 0.000014771661807357044,
      "priceChange24h": -95.869,
      "marketCapUsd": 14771.66181,
      "volume24hUsd": 953410.945306403,
      "liquidityUsd": 10895.9233,
      "lastUpdated": "2026-05-25T08:15:03.080Z",
      "sources": [
        "gecko-terminal"
      ],
      "confidence": 1
    },
    {
      "rank": 8,
      "name": "Bankcoin",
      "symbol": "BANK",
      "mint": "2jCt3hj9vd7YpV7Sr3VA5nk3tdSpJtZezeoJXW4Xpump",
      "imageUrl": "https://assets.geckoterminal.com/58c4u8r6fics1bx50m4muyosfzl3",
      "pumpFunUrl": "https://pump.fun/coin/2jCt3hj9vd7YpV7Sr3VA5nk3tdSpJtZezeoJXW4Xpump",
      "fallbackUrl": "https://www.geckoterminal.com/solana/pools/Au6S1Lr73jmmqfXUR7VTugsmmy74Jix4w8YUhe9PwPrj",
      "label": "Low-cap discovery",
      "sourceName": "GeckoTerminal",
      "priceUsd": 0.0004259826724327919,
      "priceChange24h": -46.853,
      "marketCapUsd": 425982.6724,
      "volume24hUsd": 899010.042174972,
      "liquidityUsd": 85278.1122,
      "lastUpdated": "2026-05-25T08:15:03.080Z",
      "sources": [
        "gecko-terminal"
      ],
      "confidence": 1
    },
    {
      "rank": 9,
      "name": "Boomerang",
      "symbol": "BOOMERANG",
      "mint": "BwEyBmL9drBdo4XJno8iGRvjiZcGL9FvUnq6xVNhpump",
      "imageUrl": "https://assets.geckoterminal.com/53i40w7sxtnczopahy4f5giaz4m0",
      "pumpFunUrl": "https://pump.fun/coin/BwEyBmL9drBdo4XJno8iGRvjiZcGL9FvUnq6xVNhpump",
      "fallbackUrl": "https://www.geckoterminal.com/solana/pools/9GS19u3ZuY8M4UjQoztV1xA6fNu6j9ZgUZe8jYPEy9Dp",
      "label": "Low-cap discovery",
      "sourceName": "GeckoTerminal",
      "priceUsd": 0.00005892923136160608,
      "priceChange24h": -68.743,
      "marketCapUsd": 58929.23136,
      "volume24hUsd": 816008.271115991,
      "liquidityUsd": 23444.6164,
      "lastUpdated": "2026-05-25T08:15:03.080Z",
      "sources": [
        "gecko-terminal"
      ],
      "confidence": 1
    },
    {
      "rank": 10,
      "name": "DICKMAXXING",
      "symbol": "DICKMAXX",
      "mint": "E1cdRMCYqEWE8xKxmEFmTxv6FbsfA4sK6SxCq8Rzpump",
      "imageUrl": "https://cdn.dexscreener.com/cms/images/naNmVOe-RrWg-Abp?width=800&height=800&quality=95&format=auto",
      "pumpFunUrl": "https://pump.fun/coin/E1cdRMCYqEWE8xKxmEFmTxv6FbsfA4sK6SxCq8Rzpump",
      "fallbackUrl": "https://dexscreener.com/solana/e1cdrmcyqewe8xkxmefmtxv6fbsfa4sk6sxcq8rzpump",
      "label": "Low-cap discovery",
      "sourceName": "Public meme radar",
      "priceUsd": 0.0001769,
      "priceChange24h": 404,
      "marketCapUsd": 176953,
      "volume24hUsd": 801077.73,
      "lastUpdated": "2026-05-25T08:15:02.499Z",
      "sources": [
        "dexscreener"
      ],
      "confidence": 1
    },
    {
      "rank": 11,
      "name": "Degen Coin",
      "symbol": "DEGEN",
      "mint": "FmjijgwEHpe32VPvHy1s7u7TLthh9yu1j75djVbWpump",
      "imageUrl": "https://cdn.dexscreener.com/cms/images/G6t27MFMD174fFs9?width=800&height=800&quality=95&format=auto",
      "pumpFunUrl": "https://pump.fun/coin/FmjijgwEHpe32VPvHy1s7u7TLthh9yu1j75djVbWpump",
      "fallbackUrl": "https://dexscreener.com/solana/fmjijgwehpe32vpvhy1s7u7tlthh9yu1j75djvbwpump",
      "label": "Low-cap discovery",
      "sourceName": "Public meme radar",
      "priceUsd": 0.000426,
      "priceChange24h": -27.24,
      "marketCapUsd": 426035,
      "volume24hUsd": 755434.77,
      "lastUpdated": "2026-05-25T08:15:02.498Z",
      "sources": [
        "dexscreener"
      ],
      "confidence": 1
    },
    {
      "rank": 12,
      "name": "Pumba",
      "symbol": "Pumba",
      "mint": "67SNFoWd7PfY3CwbWZAs7mWdBLQ1aPvHjbqditw1pump",
      "imageUrl": "https://cdn.dexscreener.com/cms/images/B2Hpm3aGaA84cW93?width=800&height=800&quality=95&format=auto",
      "pumpFunUrl": "https://pump.fun/coin/67SNFoWd7PfY3CwbWZAs7mWdBLQ1aPvHjbqditw1pump",
      "fallbackUrl": "https://dexscreener.com/solana/67snfowd7pfy3cwbwzas7mwdblq1apvhjbqditw1pump",
      "label": "Low-cap discovery",
      "sourceName": "Public meme radar",
      "priceUsd": 0.000008415,
      "priceChange24h": -76.08,
      "marketCapUsd": 8415,
      "volume24hUsd": 724107.87,
      "lastUpdated": "2026-05-25T08:15:02.499Z",
      "sources": [
        "dexscreener"
      ],
      "confidence": 1
    },
    {
      "rank": 13,
      "name": "Generational Wealth",
      "symbol": "GENWEALTH",
      "mint": "5gdkymiHDBetTnCBjr1YAeqMCeGJKVFRkumrAAgmpump",
      "imageUrl": "https://cdn.dexscreener.com/cms/images/_ZL__q7tb0MwO2Lu?width=800&height=800&quality=95&format=auto",
      "pumpFunUrl": "https://pump.fun/coin/5gdkymiHDBetTnCBjr1YAeqMCeGJKVFRkumrAAgmpump",
      "fallbackUrl": "https://dexscreener.com/solana/5gdkymihdbettncbjr1yaeqmcegjkvfrkumraagmpump",
      "label": "Low-cap discovery",
      "sourceName": "Public meme radar",
      "priceUsd": 0.0001173,
      "priceChange24h": 219,
      "marketCapUsd": 117396,
      "volume24hUsd": 693580.69,
      "lastUpdated": "2026-05-25T08:15:02.499Z",
      "sources": [
        "dexscreener",
        "gecko-terminal"
      ],
      "liquidityUsd": 28338.4423,
      "confidence": 2
    },
    {
      "rank": 14,
      "name": "cig",
      "symbol": "CIG",
      "mint": "cig9AXeEzQMUts9WXzmb8S5DapSVJ2b8JnrRmnWRdYz",
      "imageUrl": "https://assets.geckoterminal.com/98dpjh73cirm2pbowg9i6ze6jxjh",
      "pumpFunUrl": "",
      "fallbackUrl": "https://www.geckoterminal.com/solana/pools/B5ihVH6qRkGTXhp61MZG5rRAmaCwtva3P2gRbZZrFU65",
      "label": "Low-cap discovery",
      "sourceName": "GeckoTerminal",
      "priceUsd": 0.00023722916482144335,
      "priceChange24h": 605.264,
      "marketCapUsd": 242378.7871,
      "volume24hUsd": 651731.221741954,
      "liquidityUsd": 40546.812,
      "lastUpdated": "2026-05-25T08:15:03.080Z",
      "sources": [
        "gecko-terminal"
      ],
      "confidence": 1
    },
    {
      "rank": 15,
      "name": "OMEN",
      "symbol": "OMEN",
      "mint": "7xnopcDeghj9QTMYmKSjhJRbNvKmfnj1Qci721qrpump",
      "imageUrl": "https://assets.geckoterminal.com/o3h3uotyabdcyntmqlsp4s8k9nv6",
      "pumpFunUrl": "https://pump.fun/coin/7xnopcDeghj9QTMYmKSjhJRbNvKmfnj1Qci721qrpump",
      "fallbackUrl": "https://www.geckoterminal.com/solana/pools/7kvY3gccaGyuoS9wtmf447uVPNFonC6fs1P36R8BdgRd",
      "label": "Low-cap discovery",
      "sourceName": "GeckoTerminal",
      "priceUsd": 0.000031203486203448995,
      "priceChange24h": -86.046,
      "marketCapUsd": 31203.4862,
      "volume24hUsd": 621954.453195397,
      "liquidityUsd": 14922.7908,
      "lastUpdated": "2026-05-25T08:15:03.080Z",
      "sources": [
        "gecko-terminal"
      ],
      "confidence": 1
    },
    {
      "rank": 16,
      "name": "ENHANCED",
      "symbol": "ENHANCED",
      "mint": "GToeYaM2ZzBZw2WsZeq4edjSdD9KUfRezqYVx5Hdpump",
      "imageUrl": "https://cdn.dexscreener.com/cms/images/3KoyRx0yqasVvQlh?width=800&height=800&quality=95&format=auto",
      "pumpFunUrl": "https://pump.fun/coin/GToeYaM2ZzBZw2WsZeq4edjSdD9KUfRezqYVx5Hdpump",
      "fallbackUrl": "https://dexscreener.com/solana/gtoeyam2zzbzw2wszeq4edjsdd9kufrezqyvx5hdpump",
      "label": "Low-cap discovery",
      "sourceName": "Public meme radar",
      "priceUsd": 0.00001064,
      "priceChange24h": -69.61,
      "marketCapUsd": 10646,
      "volume24hUsd": 602657.95,
      "lastUpdated": "2026-05-25T08:15:02.499Z",
      "sources": [
        "dexscreener"
      ],
      "confidence": 1
    },
    {
      "rank": 17,
      "name": "Bitcoin Bank",
      "symbol": "BTCBANK",
      "mint": "9s96G11xGsHczudfJqKQzQxzvubQgJXSySJ1wRgxpump",
      "imageUrl": "https://coin-images.coingecko.com/coins/images/102173450/large/4vzh7918x180uh7019cfmpfhsty5.?1779609540",
      "pumpFunUrl": "https://pump.fun/coin/9s96G11xGsHczudfJqKQzQxzvubQgJXSySJ1wRgxpump",
      "fallbackUrl": "https://www.geckoterminal.com/solana/pools/4a2acVjBJysaUeEwedivQHcMNftY2EF49eayYxSwdMt2",
      "label": "Low-cap discovery",
      "sourceName": "GeckoTerminal",
      "priceUsd": 0.0001925876982754327,
      "priceChange24h": 5.47,
      "marketCapUsd": 192579.137056337,
      "volume24hUsd": 594423.176195699,
      "liquidityUsd": 40172.9821,
      "coingeckoId": "bitcoin-bank",
      "lastUpdated": "2026-05-25T08:15:03.080Z",
      "sources": [
        "gecko-terminal"
      ],
      "confidence": 1
    },
    {
      "rank": 18,
      "name": "Maybe This Is The One",
      "symbol": "THEONE",
      "mint": "FMsL3bkizj3523TtFhUgXNJPLF6jqv7cYv3jPnJApump",
      "imageUrl": "https://cdn.dexscreener.com/cms/images/hCzB9U5lQvnMChHJ?width=800&height=800&quality=95&format=auto",
      "pumpFunUrl": "https://pump.fun/coin/FMsL3bkizj3523TtFhUgXNJPLF6jqv7cYv3jPnJApump",
      "fallbackUrl": "https://dexscreener.com/solana/fmsl3bkizj3523ttfhugxnjplf6jqv7cyv3jpnjapump",
      "label": "Low-cap discovery",
      "sourceName": "Public meme radar",
      "priceUsd": 0.00001815,
      "priceChange24h": -48.85,
      "marketCapUsd": 17716,
      "volume24hUsd": 546946.69,
      "lastUpdated": "2026-05-25T08:15:02.496Z",
      "sources": [
        "dexscreener"
      ],
      "confidence": 1
    },
    {
      "rank": 19,
      "name": "Affirm",
      "symbol": "AFFIRM",
      "mint": "6upR4PbZwdHrY6TfJpeygUoQMEkmLMdStoBQqimTpump",
      "imageUrl": "https://cdn.dexscreener.com/cms/images/pGA3mRIMYkcHf4AL?width=800&height=800&quality=95&format=auto",
      "pumpFunUrl": "https://pump.fun/coin/6upR4PbZwdHrY6TfJpeygUoQMEkmLMdStoBQqimTpump",
      "fallbackUrl": "https://dexscreener.com/solana/6upr4pbzwdhry6tfjpeyguoqmekmlmdstobqqimtpump",
      "label": "Low-cap discovery",
      "sourceName": "Public meme radar",
      "priceUsd": 0.0000859,
      "priceChange24h": 143,
      "marketCapUsd": 85906,
      "volume24hUsd": 346443.07,
      "lastUpdated": "2026-05-25T08:15:02.500Z",
      "sources": [
        "dexscreener"
      ],
      "confidence": 1
    },
    {
      "rank": 20,
      "name": "CAPCAT",
      "symbol": "CAP",
      "mint": "8Zrbh9DJFgY5H6jqZb3CWeMF6wLGMHiDKvkK4qSTpump",
      "imageUrl": "https://cdn.dexscreener.com/cms/images/YKJ9DxATfhQGROCh?width=800&height=800&quality=95&format=auto",
      "pumpFunUrl": "https://pump.fun/coin/8Zrbh9DJFgY5H6jqZb3CWeMF6wLGMHiDKvkK4qSTpump",
      "fallbackUrl": "https://dexscreener.com/solana/8zrbh9djfgy5h6jqzb3cwemf6wlgmhidkvkk4qstpump",
      "label": "Low-cap discovery",
      "sourceName": "Public meme radar",
      "priceUsd": 0.0002338,
      "priceChange24h": -7.97,
      "marketCapUsd": 233834,
      "volume24hUsd": 346187.24,
      "lastUpdated": "2026-05-25T08:15:02.499Z",
      "sources": [
        "dexscreener"
      ],
      "confidence": 1
    },
    {
      "rank": 21,
      "name": "Summer26",
      "symbol": "Summer26",
      "mint": "BbnsAS3r2RNBLxCU1n6dBXzXZBQAPEQC5w82Czsspump",
      "imageUrl": "https://cdn.dexscreener.com/cms/images/vFssBkTklh1YoRdC?width=800&height=800&quality=95&format=auto",
      "pumpFunUrl": "https://pump.fun/coin/BbnsAS3r2RNBLxCU1n6dBXzXZBQAPEQC5w82Czsspump",
      "fallbackUrl": "https://dexscreener.com/solana/bbnsas3r2rnblxcu1n6dbxzxzbqapeqc5w82czsspump",
      "label": "Low-cap discovery",
      "sourceName": "Public meme radar",
      "priceUsd": 0.00003548,
      "priceChange24h": 1.07,
      "marketCapUsd": 35482,
      "volume24hUsd": 332011.46,
      "lastUpdated": "2026-05-25T08:15:02.499Z",
      "sources": [
        "dexscreener"
      ],
      "confidence": 1
    },
    {
      "rank": 22,
      "name": "Baby Troll",
      "symbol": "BABYTROLL",
      "mint": "6qdzMx4c9rL2X3Ns3SwZ8uEo4zReDPjdXpAEmpo7pump",
      "imageUrl": "https://cdn.dexscreener.com/cms/images/f2RfNFyWKgKBvyot?width=800&height=800&quality=95&format=auto",
      "pumpFunUrl": "https://pump.fun/coin/6qdzMx4c9rL2X3Ns3SwZ8uEo4zReDPjdXpAEmpo7pump",
      "fallbackUrl": "https://dexscreener.com/solana/6qdzmx4c9rl2x3ns3swz8ueo4zredpjdxpaempo7pump",
      "label": "Low-cap discovery",
      "sourceName": "Public meme radar",
      "priceUsd": 0.000495,
      "priceChange24h": -30.39,
      "marketCapUsd": 485663,
      "volume24hUsd": 251244.89,
      "lastUpdated": "2026-05-25T08:15:02.499Z",
      "sources": [
        "dexscreener"
      ],
      "confidence": 1
    },
    {
      "rank": 23,
      "name": "The Monolithic 4",
      "symbol": "四",
      "mint": "7MZpv4EynxEh2SyUTeJroNsJ4NfntHS8McN28eXSpump",
      "imageUrl": "https://cdn.dexscreener.com/cms/images/f7ars0qTrp1In1sy?width=800&height=800&quality=95&format=auto",
      "pumpFunUrl": "https://pump.fun/coin/7MZpv4EynxEh2SyUTeJroNsJ4NfntHS8McN28eXSpump",
      "fallbackUrl": "https://dexscreener.com/solana/7mzpv4eynxeh2syutejronsj4nfnths8mcn28exspump",
      "label": "Low-cap discovery",
      "sourceName": "Public meme radar",
      "priceUsd": 0.00001543,
      "priceChange24h": -56.3,
      "marketCapUsd": 15431,
      "volume24hUsd": 210906.06,
      "lastUpdated": "2026-05-25T08:15:02.500Z",
      "sources": [
        "dexscreener"
      ],
      "confidence": 1
    },
    {
      "rank": 24,
      "name": "The Tesla Squirrel",
      "symbol": "TNUT",
      "mint": "4ZzBD4eQF8CuvrHumVqccfD35QpN7jUnsghpwc1tpump",
      "imageUrl": "https://cdn.dexscreener.com/cms/images/pTDjTCb9XHEEWiY2?width=800&height=800&quality=95&format=auto",
      "pumpFunUrl": "https://pump.fun/coin/4ZzBD4eQF8CuvrHumVqccfD35QpN7jUnsghpwc1tpump",
      "fallbackUrl": "https://dexscreener.com/solana/4zzbd4eqf8cuvrhumvqccfd35qpn7junsghpwc1tpump",
      "label": "Low-cap discovery",
      "sourceName": "Public meme radar",
      "priceUsd": 0.00004731,
      "priceChange24h": 34.1,
      "marketCapUsd": 47310,
      "volume24hUsd": 191848.21,
      "lastUpdated": "2026-05-25T08:15:02.500Z",
      "sources": [
        "dexscreener"
      ],
      "confidence": 1
    },
    {
      "rank": 25,
      "name": "Troll Cup",
      "symbol": "TROLL CUP",
      "mint": "67nDo3T2wGSS6SvBa64y3ASUrqvVwReVkhnnJJ39pump",
      "imageUrl": "https://cdn.dexscreener.com/cms/images/oJV_dmdxcj-JloJf?width=800&height=800&quality=95&format=auto",
      "pumpFunUrl": "https://pump.fun/coin/67nDo3T2wGSS6SvBa64y3ASUrqvVwReVkhnnJJ39pump",
      "fallbackUrl": "https://dexscreener.com/solana/67ndo3t2wgss6svba64y3asurqvvwrevkhnnjj39pump",
      "label": "Low-cap discovery",
      "sourceName": "Public meme radar",
      "priceUsd": 0.0001113,
      "priceChange24h": 214,
      "marketCapUsd": 111379,
      "volume24hUsd": 190256.54,
      "lastUpdated": "2026-05-25T08:15:02.499Z",
      "sources": [
        "dexscreener"
      ],
      "confidence": 1
    },
    {
      "rank": 26,
      "name": "had to take profits sir",
      "symbol": "https",
      "mint": "7sGdNQSvUGpahh6qyXB3g5gsdK9FAzZM299KyCXspump",
      "imageUrl": "https://cdn.dexscreener.com/cms/images/108f6ca8e68018278057bc46b1507ecec55e2a0d5f233acb4727338efc52f92a?width=800&height=800&quality=95&format=auto",
      "pumpFunUrl": "https://pump.fun/coin/7sGdNQSvUGpahh6qyXB3g5gsdK9FAzZM299KyCXspump",
      "fallbackUrl": "https://dexscreener.com/solana/7sgdnqsvugpahh6qyxb3g5gsdk9fazzm299kycxspump",
      "label": "Low-cap discovery",
      "sourceName": "Public meme radar",
      "priceUsd": 0.0003535,
      "priceChange24h": -34.19,
      "marketCapUsd": 353352,
      "volume24hUsd": 171969.72,
      "lastUpdated": "2026-05-25T08:15:02.499Z",
      "sources": [
        "dexscreener"
      ],
      "confidence": 1
    },
    {
      "rank": 27,
      "name": "ViralRush Fund",
      "symbol": "ViralRush",
      "mint": "62PptxVdVzwf7Fpx9hAZFTJ58tg1uw4Tq8fbVhRYpump",
      "imageUrl": "https://cdn.dexscreener.com/cms/images/-JU626MY79KtVQdE?width=800&height=800&quality=95&format=auto",
      "pumpFunUrl": "https://pump.fun/coin/62PptxVdVzwf7Fpx9hAZFTJ58tg1uw4Tq8fbVhRYpump",
      "fallbackUrl": "https://dexscreener.com/solana/62pptxvdvzwf7fpx9hazftj58tg1uw4tq8fbvhrypump",
      "label": "Low-cap discovery",
      "sourceName": "Public meme radar",
      "priceUsd": 0.00002051,
      "priceChange24h": -41.95,
      "marketCapUsd": 20518,
      "volume24hUsd": 156019.82,
      "lastUpdated": "2026-05-25T08:15:02.500Z",
      "sources": [
        "dexscreener"
      ],
      "confidence": 1
    },
    {
      "rank": 28,
      "name": "Asimov",
      "symbol": "ASIMOV",
      "mint": "BxsSBSXJJZieNa7NA9FAJVAQC5KbZSXPgRfxrr9Mpump",
      "imageUrl": "https://cdn.dexscreener.com/cms/images/KCXI9nOIId9JRvbJ?width=800&height=800&quality=95&format=auto",
      "pumpFunUrl": "https://pump.fun/coin/BxsSBSXJJZieNa7NA9FAJVAQC5KbZSXPgRfxrr9Mpump",
      "fallbackUrl": "https://dexscreener.com/solana/bxssbsxjjziena7na9fajvaqc5kbzsxpgrfxrr9mpump",
      "label": "Low-cap discovery",
      "sourceName": "Public meme radar",
      "priceUsd": 0.000005817,
      "priceChange24h": -83.6,
      "marketCapUsd": 5438,
      "volume24hUsd": 118658.97,
      "lastUpdated": "2026-05-25T08:15:02.500Z",
      "sources": [
        "dexscreener"
      ],
      "confidence": 1
    },
    {
      "rank": 29,
      "name": "Cat Take Over",
      "symbol": "CTO",
      "mint": "7sShcAa4GbiSrGyMHCUUFWwBd3zZhF8gTR2LFmo4pump",
      "imageUrl": "https://cdn.dexscreener.com/cms/images/T1BOnmXpXm6YR5ff?width=800&height=800&quality=95&format=auto",
      "pumpFunUrl": "https://pump.fun/coin/7sShcAa4GbiSrGyMHCUUFWwBd3zZhF8gTR2LFmo4pump",
      "fallbackUrl": "https://dexscreener.com/solana/7sshcaa4gbisrgymhcuufwwbd3zzhf8gtr2lfmo4pump",
      "label": "Low-cap discovery",
      "sourceName": "Public meme radar",
      "priceUsd": 0.00001383,
      "priceChange24h": -60.9,
      "marketCapUsd": 13114,
      "volume24hUsd": 113667.17,
      "lastUpdated": "2026-05-25T08:15:02.500Z",
      "sources": [
        "dexscreener"
      ],
      "confidence": 1
    },
    {
      "rank": 30,
      "name": "forg",
      "symbol": "FORG",
      "mint": "7NeQaB9aSU4iTKyv9onCp9RUPY4pj33ecacX6AKLpump",
      "imageUrl": "https://cdn.dexscreener.com/cms/images/x3Rn4V40QthZfeSW?width=800&height=800&quality=95&format=auto",
      "pumpFunUrl": "https://pump.fun/coin/7NeQaB9aSU4iTKyv9onCp9RUPY4pj33ecacX6AKLpump",
      "fallbackUrl": "https://dexscreener.com/solana/7neqab9asu4itkyv9oncp9rupy4pj33ecacx6aklpump",
      "label": "Low-cap discovery",
      "sourceName": "Public meme radar",
      "priceUsd": 0.000007824,
      "priceChange24h": 196,
      "marketCapUsd": 7824.99,
      "volume24hUsd": 109364.45,
      "lastUpdated": "2026-05-25T08:15:02.500Z",
      "sources": [
        "dexscreener"
      ],
      "confidence": 1
    }
  ]
}
